{
"meta":{"test_sets":[],"test_metrics":[],"learn_metrics":[{"best_value":"Min","name":"RMSE"}],"launch_mode":"Train","parameters":"","iteration_count":1000,"learn_sets":["learn"],"name":"experiment"},
"iterations":[
{"learn":[8.211767605],"iteration":0,"passed_time":0.06410927265,"remaining_time":64.04516338},
{"learn":[7.70857799],"iteration":1,"passed_time":0.06810182151,"remaining_time":33.98280893},
{"learn":[7.234831189],"iteration":2,"passed_time":0.07180750683,"remaining_time":23.8640281},
{"learn":[6.799474238],"iteration":3,"passed_time":0.0753174083,"remaining_time":18.75403467},
{"learn":[6.388394546],"iteration":4,"passed_time":0.07878060331,"remaining_time":15.67734006},
{"learn":[6.015175859],"iteration":5,"passed_time":0.08218446735,"remaining_time":13.61522676},
{"learn":[5.640378505],"iteration":6,"passed_time":0.08553116701,"remaining_time":12.13320698},
{"learn":[5.311821944],"iteration":7,"passed_time":0.08904331839,"remaining_time":11.04137148},
{"learn":[5.005775027],"iteration":8,"passed_time":0.09208190535,"remaining_time":10.13924091},
{"learn":[4.702711448],"iteration":9,"passed_time":0.0955082685,"remaining_time":9.455318581},
{"learn":[4.432201007],"iteration":10,"passed_time":0.09870901565,"remaining_time":8.874837862},
{"learn":[4.18657622],"iteration":11,"passed_time":0.1022445828,"remaining_time":8.418137314},
{"learn":[3.941989325],"iteration":12,"passed_time":0.1057069445,"remaining_time":8.025596476},
{"learn":[3.708099918],"iteration":13,"passed_time":0.109066102,"remaining_time":7.681369752},
{"learn":[3.490422043],"iteration":14,"passed_time":0.112395969,"remaining_time":7.380668628},
{"learn":[3.291237882],"iteration":15,"passed_time":0.1157149614,"remaining_time":7.116470126},
{"learn":[3.106118633],"iteration":16,"passed_time":0.1190566612,"remaining_time":6.884276353},
{"learn":[2.936959703],"iteration":17,"passed_time":0.1221929943,"remaining_time":6.666306689},
{"learn":[2.774498363],"iteration":18,"passed_time":0.1255359858,"remaining_time":6.481621161},
{"learn":[2.627010663],"iteration":19,"passed_time":0.1289838481,"remaining_time":6.320208555},
{"learn":[2.489113024],"iteration":20,"passed_time":0.132389837,"remaining_time":6.171888116},
{"learn":[2.361538134],"iteration":21,"passed_time":0.135736745,"remaining_time":6.034115301},
{"learn":[2.24296718],"iteration":22,"passed_time":0.1390179889,"remaining_time":5.9052424},
{"learn":[2.127143663],"iteration":23,"passed_time":0.142270109,"remaining_time":5.785651101},
{"learn":[2.022071234],"iteration":24,"passed_time":0.1453383198,"remaining_time":5.668194473},
{"learn":[1.924015896],"iteration":25,"passed_time":0.1484840275,"remaining_time":5.562440108},
{"learn":[1.828532108],"iteration":26,"passed_time":0.1518086447,"remaining_time":5.470733752},
{"learn":[1.738053762],"iteration":27,"passed_time":0.1555363708,"remaining_time":5.399334016},
{"learn":[1.655538573],"iteration":28,"passed_time":0.1588525717,"remaining_time":5.318822315},
{"learn":[1.574655105],"iteration":29,"passed_time":0.1620996087,"remaining_time":5.24122068},
{"learn":[1.505006459],"iteration":30,"passed_time":0.1651009471,"remaining_time":5.160736057},
{"learn":[1.434676931],"iteration":31,"passed_time":0.1681301595,"remaining_time":5.085937324},
{"learn":[1.372889063],"iteration":32,"passed_time":0.1713951541,"remaining_time":5.022397393},
{"learn":[1.315735579],"iteration":33,"passed_time":0.1746620652,"remaining_time":4.9624575},
{"learn":[1.259459248],"iteration":34,"passed_time":0.1775616994,"remaining_time":4.895629712},
{"learn":[1.207175257],"iteration":35,"passed_time":0.1808236941,"remaining_time":4.842056698},
{"learn":[1.15904814],"iteration":36,"passed_time":0.1839930675,"remaining_time":4.788792541},
{"learn":[1.115800134],"iteration":37,"passed_time":0.1872863943,"remaining_time":4.74130293},
{"learn":[1.074635814],"iteration":38,"passed_time":0.1905084323,"remaining_time":4.694323165},
{"learn":[1.037533365],"iteration":39,"passed_time":0.1940162922,"remaining_time":4.656391012},
{"learn":[1.003051687],"iteration":40,"passed_time":0.1970577957,"remaining_time":4.609229904},
{"learn":[0.9724177635],"iteration":41,"passed_time":0.2002597511,"remaining_time":4.567829561},
{"learn":[0.9413084406],"iteration":42,"passed_time":0.2033497944,"remaining_time":4.525715191},
{"learn":[0.9145417933],"iteration":43,"passed_time":0.2065338755,"remaining_time":4.487417841},
{"learn":[0.8883790593],"iteration":44,"passed_time":0.2096064611,"remaining_time":4.448314897},
{"learn":[0.8673187529],"iteration":45,"passed_time":0.2130303244,"remaining_time":4.418063684},
{"learn":[0.8437684458],"iteration":46,"passed_time":0.216312235,"remaining_time":4.386075743},
{"learn":[0.823102613],"iteration":47,"passed_time":0.2197136824,"remaining_time":4.357654701},
{"learn":[0.8042037371],"iteration":48,"passed_time":0.2230414662,"remaining_time":4.32882519},
{"learn":[0.7872691925],"iteration":49,"passed_time":0.2266715712,"remaining_time":4.306759852},
{"learn":[0.771074274],"iteration":50,"passed_time":0.2300608108,"remaining_time":4.280935479},
{"learn":[0.7568458704],"iteration":51,"passed_time":0.2335057565,"remaining_time":4.256989561},
{"learn":[0.742306512],"iteration":52,"passed_time":0.2371026545,"remaining_time":4.236532337},
{"learn":[0.7276156362],"iteration":53,"passed_time":0.2404478126,"remaining_time":4.212289457},
{"learn":[0.7132200558],"iteration":54,"passed_time":0.243574271,"remaining_time":4.185048839},
{"learn":[0.7006730527],"iteration":55,"passed_time":0.2466530647,"remaining_time":4.157865948},
{"learn":[0.6887379943],"iteration":56,"passed_time":0.2501148431,"remaining_time":4.137864861},
{"learn":[0.6781919172],"iteration":57,"passed_time":0.2536537434,"remaining_time":4.119686661},
{"learn":[0.6681094795],"iteration":58,"passed_time":0.2568219502,"remaining_time":4.09609246},
{"learn":[0.6585041862],"iteration":59,"passed_time":0.259964408,"remaining_time":4.072775726},
{"learn":[0.6488422396],"iteration":60,"passed_time":0.2631858627,"remaining_time":4.051336477},
{"learn":[0.640319525],"iteration":61,"passed_time":0.2662016172,"remaining_time":4.027372854},
{"learn":[0.6330308002],"iteration":62,"passed_time":0.2694806529,"remaining_time":4.007990029},
{"learn":[0.6266998619],"iteration":63,"passed_time":0.2728183113,"remaining_time":3.989967803},
{"learn":[0.6175518437],"iteration":64,"passed_time":0.2760750562,"remaining_time":3.971233501},
{"learn":[0.6097919996],"iteration":65,"passed_time":0.2792239304,"remaining_time":3.951441682},
{"learn":[0.6031129928],"iteration":66,"passed_time":0.2823804294,"remaining_time":3.932252845},
{"learn":[0.5968186314],"iteration":67,"passed_time":0.2857150878,"remaining_time":3.91597738},
{"learn":[0.5895407647],"iteration":68,"passed_time":0.2890412883,"remaining_time":3.89996289},
{"learn":[0.5837918098],"iteration":69,"passed_time":0.2922384523,"remaining_time":3.88259658},
{"learn":[0.5772472953],"iteration":70,"passed_time":0.2954746563,"remaining_time":3.866140222},
{"learn":[0.5730483509],"iteration":71,"passed_time":0.2988013151,"remaining_time":3.851216951},
{"learn":[0.5686162461],"iteration":72,"passed_time":0.3020663514,"remaining_time":3.835828873},
{"learn":[0.5634050391],"iteration":73,"passed_time":0.3054553827,"remaining_time":3.822320059},
{"learn":[0.5569036814],"iteration":74,"passed_time":0.3084228475,"remaining_time":3.803881786},
{"learn":[0.5529572075],"iteration":75,"passed_time":0.3116497603,"remaining_time":3.78900498},
{"learn":[0.5472870637],"iteration":76,"passed_time":0.315136871,"remaining_time":3.777549765},
{"learn":[0.5417560461],"iteration":77,"passed_time":0.3183617838,"remaining_time":3.763199547},
{"learn":[0.5363244686],"iteration":78,"passed_time":0.3215672391,"remaining_time":3.748904142},
{"learn":[0.5329754414],"iteration":79,"passed_time":0.3249839777,"remaining_time":3.737315743},
{"learn":[0.5304557756],"iteration":80,"passed_time":0.328196266,"remaining_time":3.723609487},
{"learn":[0.5236279621],"iteration":81,"passed_time":0.3314558858,"remaining_time":3.710689063},
{"learn":[0.5201623443],"iteration":82,"passed_time":0.3346944231,"remaining_time":3.697768506},
{"learn":[0.5157593732],"iteration":83,"passed_time":0.3380421644,"remaining_time":3.686269317},
{"learn":[0.5114953211],"iteration":84,"passed_time":0.341316492,"remaining_time":3.674171649},
{"learn":[0.5079872779],"iteration":85,"passed_time":0.3443604121,"remaining_time":3.659830426},
{"learn":[0.5055684218],"iteration":86,"passed_time":0.3475129945,"remaining_time":3.646889241},
{"learn":[0.5006581362],"iteration":87,"passed_time":0.3509324829,"remaining_time":3.636936641},
{"learn":[0.496876055],"iteration":88,"passed_time":0.3542624332,"remaining_time":3.626214344},
{"learn":[0.4936363767],"iteration":89,"passed_time":0.3574436811,"remaining_time":3.614152776},
{"learn":[0.4907406633],"iteration":90,"passed_time":0.360602055,"remaining_time":3.60205789},
{"learn":[0.4874689685],"iteration":91,"passed_time":0.3638048854,"remaining_time":3.590596043},
{"learn":[0.4855316361],"iteration":92,"passed_time":0.3671577931,"remaining_time":3.580775466},
{"learn":[0.4826442618],"iteration":93,"passed_time":0.3706452788,"remaining_time":3.572389602},
{"learn":[0.4805399706],"iteration":94,"passed_time":0.373644409,"remaining_time":3.559454634},
{"learn":[0.4781292589],"iteration":95,"passed_time":0.3768529476,"remaining_time":3.54869859},
{"learn":[0.4757580047],"iteration":96,"passed_time":0.3798367867,"remaining_time":3.536006375},
{"learn":[0.473442855],"iteration":97,"passed_time":0.3832821074,"remaining_time":3.527759805},
{"learn":[0.4688210358],"iteration":98,"passed_time":0.38759781,"remaining_time":3.527531584},
{"learn":[0.4668531826],"iteration":99,"passed_time":0.3912487892,"remaining_time":3.521239103},
{"learn":[0.4638922966],"iteration":100,"passed_time":0.3945718232,"remaining_time":3.512079891},
{"learn":[0.4615163487],"iteration":101,"passed_time":0.3975678702,"remaining_time":3.500156347},
{"learn":[0.4586973926],"iteration":102,"passed_time":0.4007722422,"remaining_time":3.4902204},
{"learn":[0.4553967655],"iteration":103,"passed_time":0.4037810803,"remaining_time":3.478729307},
{"learn":[0.4512025634],"iteration":104,"passed_time":0.4070420334,"remaining_time":3.469548761},
{"learn":[0.4467980796],"iteration":105,"passed_time":0.4103089862,"remaining_time":3.460530507},
{"learn":[0.4447923141],"iteration":106,"passed_time":0.4133641142,"remaining_time":3.449851906},
{"learn":[0.4429730306],"iteration":107,"passed_time":0.4166075263,"remaining_time":3.440869569},
{"learn":[0.4400879757],"iteration":108,"passed_time":0.4201560513,"remaining_time":3.434486621},
{"learn":[0.4362010969],"iteration":109,"passed_time":0.4235257083,"remaining_time":3.426708004},
{"learn":[0.4341285628],"iteration":110,"passed_time":0.4266557083,"remaining_time":3.417089412},
{"learn":[0.4307972771],"iteration":111,"passed_time":0.4300211156,"remaining_time":3.40945313},
{"learn":[0.4285662798],"iteration":112,"passed_time":0.4335599742,"remaining_time":3.403253957},
{"learn":[0.4272043516],"iteration":113,"passed_time":0.4367267227,"remaining_time":3.394209441},
{"learn":[0.4242209234],"iteration":114,"passed_time":0.4400714225,"remaining_time":3.386636599},
{"learn":[0.4225346377],"iteration":115,"passed_time":0.4434562039,"remaining_time":3.379442106},
{"learn":[0.4206335477],"iteration":116,"passed_time":0.4471103496,"remaining_time":3.37434563},
{"learn":[0.4181509075],"iteration":117,"passed_time":0.4506863318,"remaining_time":3.368689361},
{"learn":[0.4162074484],"iteration":118,"passed_time":0.4540183654,"remaining_time":3.361262016},
{"learn":[0.4139408393],"iteration":119,"passed_time":0.4574881435,"remaining_time":3.354913052},
{"learn":[0.412493079],"iteration":120,"passed_time":0.460570687,"remaining_time":3.345798627},
{"learn":[0.4109515112],"iteration":121,"passed_time":0.4641315031,"remaining_time":3.34022508},
{"learn":[0.4097397052],"iteration":122,"passed_time":0.4671417995,"remaining_time":3.33075901},
{"learn":[0.4082197293],"iteration":123,"passed_time":0.4701400131,"remaining_time":3.321311705},
{"learn":[0.4061886284],"iteration":124,"passed_time":0.4731651423,"remaining_time":3.312155996},
{"learn":[0.4050226634],"iteration":125,"passed_time":0.4762093124,"remaining_time":3.303229675},
{"learn":[0.4023454441],"iteration":126,"passed_time":0.4794660573,"remaining_time":3.295857228},
{"learn":[0.3988991607],"iteration":127,"passed_time":0.4826651378,"remaining_time":3.288156251},
{"learn":[0.3971373111],"iteration":128,"passed_time":0.4858872591,"remaining_time":3.280680641},
{"learn":[0.3945462127],"iteration":129,"passed_time":0.4894004521,"remaining_time":3.27521841},
{"learn":[0.3920527631],"iteration":130,"passed_time":0.4925628258,"remaining_time":3.267458745},
{"learn":[0.3897686813],"iteration":131,"passed_time":0.4959339828,"remaining_time":3.261141645},
{"learn":[0.3871114899],"iteration":132,"passed_time":0.4991726035,"remaining_time":3.254004866},
{"learn":[0.384479171],"iteration":133,"passed_time":0.5026347569,"remaining_time":3.248370891},
{"learn":[0.3827244591],"iteration":134,"passed_time":0.5058256711,"remaining_time":3.241031152},
{"learn":[0.3818569202],"iteration":135,"passed_time":0.5089377968,"remaining_time":3.233251885},
{"learn":[0.3801038628],"iteration":136,"passed_time":0.5121665845,"remaining_time":3.226275638},
{"learn":[0.3781966441],"iteration":137,"passed_time":0.5156237797,"remaining_time":3.220780421},
{"learn":[0.3764939889],"iteration":138,"passed_time":0.5188649419,"remaining_time":3.213976367},
{"learn":[0.3752883088],"iteration":139,"passed_time":0.5224331744,"remaining_time":3.209232357},
{"learn":[0.3733699279],"iteration":140,"passed_time":0.5257829156,"remaining_time":3.203173933},
{"learn":[0.3720634501],"iteration":141,"passed_time":0.5292270697,"remaining_time":3.197724125},
{"learn":[0.3701060498],"iteration":142,"passed_time":0.5333209062,"remaining_time":3.19619592},
{"learn":[0.3683837536],"iteration":143,"passed_time":0.5375699865,"remaining_time":3.195554919},
{"learn":[0.3663731904],"iteration":144,"passed_time":0.5416535733,"remaining_time":3.193888312},
{"learn":[0.364864258],"iteration":145,"passed_time":0.545760451,"remaining_time":3.19232483},
{"learn":[0.3636495721],"iteration":146,"passed_time":0.5494988433,"remaining_time":3.188588526},
{"learn":[0.3623637709],"iteration":147,"passed_time":0.5529929954,"remaining_time":3.183446163},
{"learn":[0.3622727082],"iteration":148,"passed_time":0.5560189579,"remaining_time":3.1756519},
{"learn":[0.3603832152],"iteration":149,"passed_time":0.5592341628,"remaining_time":3.168993589},
{"learn":[0.3593619009],"iteration":150,"passed_time":0.5626759837,"remaining_time":3.163655034},
{"learn":[0.3592332635],"iteration":151,"passed_time":0.5677379898,"remaining_time":3.167380364},
{"learn":[0.3574059924],"iteration":152,"passed_time":0.5728569937,"remaining_time":3.171306364},
{"learn":[0.3563853397],"iteration":153,"passed_time":0.5774243529,"remaining_time":3.172084432},
{"learn":[0.3545149377],"iteration":154,"passed_time":0.5807878436,"remaining_time":3.166230502},
{"learn":[0.3531070884],"iteration":155,"passed_time":0.5842919536,"remaining_time":3.161169287},
{"learn":[0.3516815103],"iteration":156,"passed_time":0.5874119123,"remaining_time":3.154065236},
{"learn":[0.3506412052],"iteration":157,"passed_time":0.5909511459,"remaining_time":3.14924598},
{"learn":[0.3499795735],"iteration":158,"passed_time":0.5940643966,"remaining_time":3.14218967},
{"learn":[0.3497648787],"iteration":159,"passed_time":0.5969790302,"remaining_time":3.134139908},
{"learn":[0.3489414809],"iteration":160,"passed_time":0.6006162182,"remaining_time":3.129919299},
{"learn":[0.3475723547],"iteration":161,"passed_time":0.6041009124,"remaining_time":3.124917065},
{"learn":[0.3460339438],"iteration":162,"passed_time":0.6076934355,"remaining_time":3.120487151},
{"learn":[0.3442895913],"iteration":163,"passed_time":0.6107303142,"remaining_time":3.113235017},
{"learn":[0.3419631015],"iteration":164,"passed_time":0.6140882218,"remaining_time":3.107658577},
{"learn":[0.340433642],"iteration":165,"passed_time":0.6178581962,"remaining_time":3.10417913},
{"learn":[0.3393655865],"iteration":166,"passed_time":0.62126806,"remaining_time":3.098899964},
{"learn":[0.3377852487],"iteration":167,"passed_time":0.6245269715,"remaining_time":3.092895478},
{"learn":[0.3377254861],"iteration":168,"passed_time":0.6273369009,"remaining_time":3.084715767},
{"learn":[0.3363262959],"iteration":169,"passed_time":0.6304091532,"remaining_time":3.077879983},
{"learn":[0.3351980244],"iteration":170,"passed_time":0.6339036386,"remaining_time":3.073135184},
{"learn":[0.3332547966],"iteration":171,"passed_time":0.6378055245,"remaining_time":3.070366129},
{"learn":[0.3323991758],"iteration":172,"passed_time":0.6412103885,"remaining_time":3.065208042},
{"learn":[0.3303092042],"iteration":173,"passed_time":0.6445217979,"remaining_time":3.059626466},
{"learn":[0.3302230293],"iteration":174,"passed_time":0.6473621844,"remaining_time":3.051850298},
{"learn":[0.3283978731],"iteration":175,"passed_time":0.6510577868,"remaining_time":3.048134184},
{"learn":[0.3278148959],"iteration":176,"passed_time":0.6543632798,"remaining_time":3.042604403},
{"learn":[0.3265710922],"iteration":177,"passed_time":0.6575791097,"remaining_time":3.036685551},
{"learn":[0.3258154887],"iteration":178,"passed_time":0.6610892195,"remaining_time":3.032146643},
{"learn":[0.3254637841],"iteration":179,"passed_time":0.6638572756,"remaining_time":3.0242387},
{"learn":[0.3244334624],"iteration":180,"passed_time":0.6672096417,"remaining_time":3.019031472},
{"learn":[0.3232170521],"iteration":181,"passed_time":0.6710778622,"remaining_time":3.016163139},
{"learn":[0.3231625451],"iteration":182,"passed_time":0.6743397319,"remaining_time":3.010576836},
{"learn":[0.3219177596],"iteration":183,"passed_time":0.6777448875,"remaining_time":3.00565124},
{"learn":[0.321865268],"iteration":184,"passed_time":0.6810674215,"remaining_time":3.0003781},
{"learn":[0.3207662254],"iteration":185,"passed_time":0.6844754104,"remaining_time":2.995499914},
{"learn":[0.3192115464],"iteration":186,"passed_time":0.687846984,"remaining_time":2.990479134},
{"learn":[0.3179474303],"iteration":187,"passed_time":0.6911124369,"remaining_time":2.985017547},
{"learn":[0.3154782236],"iteration":188,"passed_time":0.6945442582,"remaining_time":2.980293087},
{"learn":[0.3139607577],"iteration":189,"passed_time":0.6980882833,"remaining_time":2.976060576},
{"learn":[0.3139181415],"iteration":190,"passed_time":0.7008211741,"remaining_time":2.968399633},
{"learn":[0.3124766659],"iteration":191,"passed_time":0.7042348294,"remaining_time":2.963654907},
{"learn":[0.3110163455],"iteration":192,"passed_time":0.7072757913,"remaining_time":2.957365614},
{"learn":[0.3098300998],"iteration":193,"passed_time":0.7106276991,"remaining_time":2.952401678},
{"learn":[0.307837391],"iteration":194,"passed_time":0.7137808232,"remaining_time":2.946633655},
{"learn":[0.3065860685],"iteration":195,"passed_time":0.7173920539,"remaining_time":2.942771486},
{"learn":[0.3058739074],"iteration":196,"passed_time":0.7206692563,"remaining_time":2.937550319},
{"learn":[0.3058265822],"iteration":197,"passed_time":0.7235948478,"remaining_time":2.930924586},
{"learn":[0.3057863526],"iteration":198,"passed_time":0.7262173681,"remaining_time":2.92311614},
{"learn":[0.3047731669],"iteration":199,"passed_time":0.729782559,"remaining_time":2.919130236},
{"learn":[0.3028454855],"iteration":200,"passed_time":0.733095885,"remaining_time":2.914147324},
{"learn":[0.3008086068],"iteration":201,"passed_time":0.7361134311,"remaining_time":2.908012466},
{"learn":[0.2999311392],"iteration":202,"passed_time":0.7394485063,"remaining_time":2.903154973},
{"learn":[0.2984016401],"iteration":203,"passed_time":0.7426809188,"remaining_time":2.89791182},
{"learn":[0.2971402361],"iteration":204,"passed_time":0.7456433005,"remaining_time":2.891641092},
{"learn":[0.2966095204],"iteration":205,"passed_time":0.748775592,"remaining_time":2.886057379},
{"learn":[0.295086952],"iteration":206,"passed_time":0.7520909596,"remaining_time":2.8811987},
{"learn":[0.2950481075],"iteration":207,"passed_time":0.7548518077,"remaining_time":2.874243422},
{"learn":[0.2943053508],"iteration":208,"passed_time":0.7581324266,"remaining_time":2.869295452},
{"learn":[0.2935337876],"iteration":209,"passed_time":0.7613691307,"remaining_time":2.864198158},
{"learn":[0.2924135176],"iteration":210,"passed_time":0.7647306631,"remaining_time":2.859585276},
{"learn":[0.2916180975],"iteration":211,"passed_time":0.7685257198,"remaining_time":2.8565956},
{"learn":[0.2915806078],"iteration":212,"passed_time":0.7714195626,"remaining_time":2.850268525},
{"learn":[0.2908135959],"iteration":213,"passed_time":0.7747974277,"remaining_time":2.8457513},
{"learn":[0.2898627968],"iteration":214,"passed_time":0.7782379569,"remaining_time":2.841473471},
{"learn":[0.2886834713],"iteration":215,"passed_time":0.7814670779,"remaining_time":2.836436061},
{"learn":[0.2886477524],"iteration":216,"passed_time":0.7843303802,"remaining_time":2.830095335},
{"learn":[0.2886130198],"iteration":217,"passed_time":0.7870357305,"remaining_time":2.823219914},
{"learn":[0.2870156855],"iteration":218,"passed_time":0.7905113833,"remaining_time":2.819129636},
{"learn":[0.2855474231],"iteration":219,"passed_time":0.7935405124,"remaining_time":2.813461817},
{"learn":[0.2847100239],"iteration":220,"passed_time":0.7968797123,"remaining_time":2.808910841},
{"learn":[0.2834763386],"iteration":221,"passed_time":0.8002849513,"remaining_time":2.804602217},
{"learn":[0.282898144],"iteration":222,"passed_time":0.8033495789,"remaining_time":2.7991149},
{"learn":[0.2828642589],"iteration":223,"passed_time":0.8062525879,"remaining_time":2.793089322},
{"learn":[0.282167022],"iteration":224,"passed_time":0.8096087039,"remaining_time":2.788652202},
{"learn":[0.2810414117],"iteration":225,"passed_time":0.8129859857,"remaining_time":2.784297137},
{"learn":[0.2800022402],"iteration":226,"passed_time":0.8162703961,"remaining_time":2.779634433},
{"learn":[0.2790525675],"iteration":227,"passed_time":0.8196614274,"remaining_time":2.775344833},
{"learn":[0.2783683288],"iteration":228,"passed_time":0.8227501373,"remaining_time":2.770045222},
{"learn":[0.277579376],"iteration":229,"passed_time":0.8259440931,"remaining_time":2.765117181},
{"learn":[0.2768128796],"iteration":230,"passed_time":0.8293177917,"remaining_time":2.760802519},
{"learn":[0.2767850784],"iteration":231,"passed_time":0.8321152633,"remaining_time":2.754588458},
{"learn":[0.2767540126],"iteration":232,"passed_time":0.8348049475,"remaining_time":2.748048904},
{"learn":[0.2753449667],"iteration":233,"passed_time":0.8379936951,"remaining_time":2.743175942},
{"learn":[0.2747083881],"iteration":234,"passed_time":0.8412493151,"remaining_time":2.738535004},
{"learn":[0.2734827226],"iteration":235,"passed_time":0.8447312593,"remaining_time":2.734638484},
{"learn":[0.2734517524],"iteration":236,"passed_time":0.8478479265,"remaining_time":2.729569485},
{"learn":[0.272810883],"iteration":237,"passed_time":0.8512845392,"remaining_time":2.725541256},
{"learn":[0.2727813883],"iteration":238,"passed_time":0.8540417208,"remaining_time":2.7193546},
{"learn":[0.2727530465],"iteration":239,"passed_time":0.8569810201,"remaining_time":2.71377323},
{"learn":[0.2720900305],"iteration":240,"passed_time":0.8601238529,"remaining_time":2.70885479},
{"learn":[0.2706445703],"iteration":241,"passed_time":0.8637007933,"remaining_time":2.705310749},
{"learn":[0.269354666],"iteration":242,"passed_time":0.8667405469,"remaining_time":2.700092979},
{"learn":[0.2682643005],"iteration":243,"passed_time":0.870034082,"remaining_time":2.695679369},
{"learn":[0.2675682984],"iteration":244,"passed_time":0.8732152883,"remaining_time":2.690928746},
{"learn":[0.2675409517],"iteration":245,"passed_time":0.875941971,"remaining_time":2.684797749},
{"learn":[0.2675176434],"iteration":246,"passed_time":0.8789141857,"remaining_time":2.679442841},
{"learn":[0.2662361551],"iteration":247,"passed_time":0.8821455982,"remaining_time":2.674893104},
{"learn":[0.2654872896],"iteration":248,"passed_time":0.8853247213,"remaining_time":2.670196248},
{"learn":[0.2639766052],"iteration":249,"passed_time":0.8886467136,"remaining_time":2.665940141},
{"learn":[0.2634429862],"iteration":250,"passed_time":0.8916130118,"remaining_time":2.660630063},
{"learn":[0.2626451591],"iteration":251,"passed_time":0.8949423788,"remaining_time":2.656416267},
{"learn":[0.2615872425],"iteration":252,"passed_time":0.8984511136,"remaining_time":2.652739059},
{"learn":[0.2615634536],"iteration":253,"passed_time":0.9011611304,"remaining_time":2.646717336},
{"learn":[0.2610828815],"iteration":254,"passed_time":0.9045185796,"remaining_time":2.642613105},
{"learn":[0.2605340484],"iteration":255,"passed_time":0.9077583252,"remaining_time":2.638172633},
{"learn":[0.2605111319],"iteration":256,"passed_time":0.9107979955,"remaining_time":2.633163076},
{"learn":[0.2597133132],"iteration":257,"passed_time":0.9143183965,"remaining_time":2.629551357},
{"learn":[0.2589194741],"iteration":258,"passed_time":0.9179903332,"remaining_time":2.626373888},
{"learn":[0.2588974599],"iteration":259,"passed_time":0.9209095499,"remaining_time":2.621050257},
{"learn":[0.2582151007],"iteration":260,"passed_time":0.9242359587,"remaining_time":2.616897983},
{"learn":[0.2581937852],"iteration":261,"passed_time":0.9269928069,"remaining_time":2.611147678},
{"learn":[0.2576192646],"iteration":262,"passed_time":0.9303790883,"remaining_time":2.607183985},
{"learn":[0.2571464661],"iteration":263,"passed_time":0.9335755857,"remaining_time":2.602695572},
{"learn":[0.2571228533],"iteration":264,"passed_time":0.9361345668,"remaining_time":2.596448704},
{"learn":[0.2562590833],"iteration":265,"passed_time":0.9391018233,"remaining_time":2.591356159},
{"learn":[0.2555920644],"iteration":266,"passed_time":0.9423178615,"remaining_time":2.586962519},
{"learn":[0.2549889345],"iteration":267,"passed_time":0.9457537659,"remaining_time":2.583178196},
{"learn":[0.2541382928],"iteration":268,"passed_time":0.9488178102,"remaining_time":2.578385945},
{"learn":[0.2539598133],"iteration":269,"passed_time":0.9518301482,"remaining_time":2.573466697},
{"learn":[0.2533384101],"iteration":270,"passed_time":0.9548176539,"remaining_time":2.568494722},
{"learn":[0.2527177699],"iteration":271,"passed_time":0.9581766447,"remaining_time":2.564531608},
{"learn":[0.2521033609],"iteration":272,"passed_time":0.9615550931,"remaining_time":2.560624735},
{"learn":[0.2520745276],"iteration":273,"passed_time":0.9644351447,"remaining_time":2.55540115},
{"learn":[0.2519267512],"iteration":274,"passed_time":0.9673672776,"remaining_time":2.550331914},
{"learn":[0.250922141],"iteration":275,"passed_time":0.9705326095,"remaining_time":2.545889889},
{"learn":[0.2500183381],"iteration":276,"passed_time":0.9737198155,"remaining_time":2.541514176},
{"learn":[0.249997854],"iteration":277,"passed_time":0.9768696897,"remaining_time":2.537050058},
{"learn":[0.2496567866],"iteration":278,"passed_time":0.9801360593,"remaining_time":2.532896411},
{"learn":[0.2490255394],"iteration":279,"passed_time":0.9834444688,"remaining_time":2.528857205},
{"learn":[0.248599844],"iteration":280,"passed_time":0.986368102,"remaining_time":2.523838667},
{"learn":[0.2478196474],"iteration":281,"passed_time":0.9894699364,"remaining_time":2.519288703},
{"learn":[0.2473000311],"iteration":282,"passed_time":0.9927483472,"remaining_time":2.515196342},
{"learn":[0.2467313654],"iteration":283,"passed_time":0.9961362535,"remaining_time":2.511385766},
{"learn":[0.2467043973],"iteration":284,"passed_time":0.9992007561,"remaining_time":2.506766809},
{"learn":[0.2458673163],"iteration":285,"passed_time":1.002215719,"remaining_time":2.502035047},
{"learn":[0.2458499637],"iteration":286,"passed_time":1.005064772,"remaining_time":2.496903074},
{"learn":[0.2451926582],"iteration":287,"passed_time":1.008287185,"remaining_time":2.492709985},
{"learn":[0.2442657012],"iteration":288,"passed_time":1.01203516,"remaining_time":2.489816605},
{"learn":[0.2434003057],"iteration":289,"passed_time":1.015741637,"remaining_time":2.486815732},
{"learn":[0.2432766045],"iteration":290,"passed_time":1.019199999,"remaining_time":2.483205496},
{"learn":[0.2428700886],"iteration":291,"passed_time":1.022634987,"remaining_time":2.479539625},
{"learn":[0.2419286624],"iteration":292,"passed_time":1.026227885,"remaining_time":2.476256364},
{"learn":[0.2413522531],"iteration":293,"passed_time":1.031105857,"remaining_time":2.476056921},
{"learn":[0.2408789366],"iteration":294,"passed_time":1.03506299,"remaining_time":2.473625113},
{"learn":[0.2400620904],"iteration":295,"passed_time":1.03861339,"remaining_time":2.470215631},
{"learn":[0.2396706486],"iteration":296,"passed_time":1.083754712,"remaining_time":2.565251053},
{"learn":[0.2388437115],"iteration":297,"passed_time":1.099553248,"remaining_time":2.590222751},
{"learn":[0.2382011648],"iteration":298,"passed_time":1.105152107,"remaining_time":2.591008787},
{"learn":[0.2375270667],"iteration":299,"passed_time":1.111742469,"remaining_time":2.594065762},
{"learn":[0.2366442521],"iteration":300,"passed_time":1.11703155,"remaining_time":2.594036722},
{"learn":[0.2359058859],"iteration":301,"passed_time":1.122174219,"remaining_time":2.593634454},
{"learn":[0.2353856614],"iteration":302,"passed_time":1.128685501,"remaining_time":2.596349155},
{"learn":[0.2351104584],"iteration":303,"passed_time":1.135785051,"remaining_time":2.600349984},
{"learn":[0.234695207],"iteration":304,"passed_time":1.141912598,"remaining_time":2.602063132},
{"learn":[0.2343011427],"iteration":305,"passed_time":1.145878814,"remaining_time":2.598823193},
{"learn":[0.233583054],"iteration":306,"passed_time":1.148812072,"remaining_time":2.593246794},
{"learn":[0.2329719787],"iteration":307,"passed_time":1.1522736,"remaining_time":2.588874453},
{"learn":[0.2324607687],"iteration":308,"passed_time":1.15529523,"remaining_time":2.583524284},
{"learn":[0.2323158867],"iteration":309,"passed_time":1.158173573,"remaining_time":2.577870211},
{"learn":[0.2321625038],"iteration":310,"passed_time":1.161844885,"remaining_time":2.573990757},
{"learn":[0.2313908549],"iteration":311,"passed_time":1.165930097,"remaining_time":2.571025341},
{"learn":[0.231024212],"iteration":312,"passed_time":1.169650406,"remaining_time":2.56725185},
{"learn":[0.2303001651],"iteration":313,"passed_time":1.173684662,"remaining_time":2.56416458},
{"learn":[0.2296888375],"iteration":314,"passed_time":1.177488927,"remaining_time":2.560571158},
{"learn":[0.22933041],"iteration":315,"passed_time":1.181199528,"remaining_time":2.556773663},
{"learn":[0.2290429625],"iteration":316,"passed_time":1.184086246,"remaining_time":2.551201597},
{"learn":[0.228351849],"iteration":317,"passed_time":1.186847136,"remaining_time":2.545376562},
{"learn":[0.2279261012],"iteration":318,"passed_time":1.18999901,"remaining_time":2.54040541},
{"learn":[0.2271863011],"iteration":319,"passed_time":1.193149468,"remaining_time":2.535442619},
{"learn":[0.2271190861],"iteration":320,"passed_time":1.195726865,"remaining_time":2.529278944},
{"learn":[0.2267084767],"iteration":321,"passed_time":1.198602625,"remaining_time":2.523765775},
{"learn":[0.2261022235],"iteration":322,"passed_time":1.201903576,"remaining_time":2.519160127},
{"learn":[0.2258531858],"iteration":323,"passed_time":1.204499889,"remaining_time":2.513092362},
{"learn":[0.2252296655],"iteration":324,"passed_time":1.207435647,"remaining_time":2.507750959},
{"learn":[0.2249206375],"iteration":325,"passed_time":1.210223702,"remaining_time":2.502118943},
{"learn":[0.2243927303],"iteration":326,"passed_time":1.213090005,"remaining_time":2.496665361},
{"learn":[0.2237479611],"iteration":327,"passed_time":1.216396706,"remaining_time":2.492129836},
{"learn":[0.2232285809],"iteration":328,"passed_time":1.219888275,"remaining_time":2.487978822},
{"learn":[0.2227549965],"iteration":329,"passed_time":1.223158019,"remaining_time":2.483381433},
{"learn":[0.2222984852],"iteration":330,"passed_time":1.226751209,"remaining_time":2.479445797},
{"learn":[0.2216062763],"iteration":331,"passed_time":1.229906499,"remaining_time":2.47463115},
{"learn":[0.2215913956],"iteration":332,"passed_time":1.232688388,"remaining_time":2.469078544},
{"learn":[0.2212389635],"iteration":333,"passed_time":1.235917093,"remaining_time":2.464433484},
{"learn":[0.2206836685],"iteration":334,"passed_time":1.239696775,"remaining_time":2.460890613},
{"learn":[0.2203116963],"iteration":335,"passed_time":1.243282549,"remaining_time":2.456963132},
{"learn":[0.2197893099],"iteration":336,"passed_time":1.246603749,"remaining_time":2.452517168},
{"learn":[0.2196795585],"iteration":337,"passed_time":1.24963992,"remaining_time":2.447519606},
{"learn":[0.219583175],"iteration":338,"passed_time":1.252589593,"remaining_time":2.44236496},
{"learn":[0.2192195746],"iteration":339,"passed_time":1.255879295,"remaining_time":2.437883338},
{"learn":[0.2191714784],"iteration":340,"passed_time":1.25888205,"remaining_time":2.432854168},
{"learn":[0.2184999512],"iteration":341,"passed_time":1.262089214,"remaining_time":2.428230125},
{"learn":[0.2179871456],"iteration":342,"passed_time":1.265632156,"remaining_time":2.424257511},
{"learn":[0.2173616558],"iteration":343,"passed_time":1.268904358,"remaining_time":2.419771102},
{"learn":[0.2168069516],"iteration":344,"passed_time":1.272211476,"remaining_time":2.41535802},
{"learn":[0.2164546892],"iteration":345,"passed_time":1.275451722,"remaining_time":2.410824931},
{"learn":[0.2163574293],"iteration":346,"passed_time":1.278677301,"remaining_time":2.406271694},
{"learn":[0.2158016066],"iteration":347,"passed_time":1.281800677,"remaining_time":2.401534601},
{"learn":[0.2154944867],"iteration":348,"passed_time":1.284785099,"remaining_time":2.396547563},
{"learn":[0.2148961444],"iteration":349,"passed_time":1.288327833,"remaining_time":2.392608832},
{"learn":[0.2148776084],"iteration":350,"passed_time":1.291521538,"remaining_time":2.388027004},
{"learn":[0.2147407493],"iteration":351,"passed_time":1.295339761,"remaining_time":2.384602742},
{"learn":[0.2143451669],"iteration":352,"passed_time":1.298808206,"remaining_time":2.380535153},
{"learn":[0.214010649],"iteration":353,"passed_time":1.302313982,"remaining_time":2.376539075},
{"learn":[0.2139945418],"iteration":354,"passed_time":1.305261198,"remaining_time":2.371530909},
{"learn":[0.2139791268],"iteration":355,"passed_time":1.308091418,"remaining_time":2.366322678},
{"learn":[0.2139659471],"iteration":356,"passed_time":1.310859724,"remaining_time":2.361016254},
{"learn":[0.2139514723],"iteration":357,"passed_time":1.313513702,"remaining_time":2.355518985},
{"learn":[0.2138894659],"iteration":358,"passed_time":1.316744406,"remaining_time":2.35106731},
{"learn":[0.2137871007],"iteration":359,"passed_time":1.319667748,"remaining_time":2.346075996},
{"learn":[0.2134457521],"iteration":360,"passed_time":1.32286712,"remaining_time":2.341584735},
{"learn":[0.2130909554],"iteration":361,"passed_time":1.325889916,"remaining_time":2.336789409},
{"learn":[0.2127160566],"iteration":362,"passed_time":1.329142786,"remaining_time":2.332407588},
{"learn":[0.2122630495],"iteration":363,"passed_time":1.332730767,"remaining_time":2.328617495},
{"learn":[0.2117594633],"iteration":364,"passed_time":1.336157714,"remaining_time":2.324548352},
{"learn":[0.2112951403],"iteration":365,"passed_time":1.339146011,"remaining_time":2.319722872},
{"learn":[0.2109930962],"iteration":366,"passed_time":1.342434297,"remaining_time":2.315424822},
{"learn":[0.2109809294],"iteration":367,"passed_time":1.345166229,"remaining_time":2.310176785},
{"learn":[0.2104346637],"iteration":368,"passed_time":1.348379017,"remaining_time":2.305764661},
{"learn":[0.2101638753],"iteration":369,"passed_time":1.351646554,"remaining_time":2.30145224},
{"learn":[0.2097244005],"iteration":370,"passed_time":1.355271742,"remaining_time":2.297751821},
{"learn":[0.2093579064],"iteration":371,"passed_time":1.358936346,"remaining_time":2.294118347},
{"learn":[0.209119963],"iteration":372,"passed_time":1.362248797,"remaining_time":2.289892749},
{"learn":[0.2085961473],"iteration":373,"passed_time":1.365455085,"remaining_time":2.285494341},
{"learn":[0.2081754308],"iteration":374,"passed_time":1.368621626,"remaining_time":2.281036043},
{"learn":[0.2081611195],"iteration":375,"passed_time":1.371321768,"remaining_time":2.275810593},
{"learn":[0.2080827803],"iteration":376,"passed_time":1.374436477,"remaining_time":2.27128362},
{"learn":[0.208034601],"iteration":377,"passed_time":1.377413149,"remaining_time":2.266536981},
{"learn":[0.2077252983],"iteration":378,"passed_time":1.38077739,"remaining_time":2.262434721},
{"learn":[0.2076313811],"iteration":379,"passed_time":1.383672858,"remaining_time":2.257571505},
{"learn":[0.2072249812],"iteration":380,"passed_time":1.386622407,"remaining_time":2.252806482},
{"learn":[0.2066732829],"iteration":381,"passed_time":1.389847861,"remaining_time":2.248497325},
{"learn":[0.2063976819],"iteration":382,"passed_time":1.393050483,"remaining_time":2.244157045},
{"learn":[0.2058993521],"iteration":383,"passed_time":1.396330477,"remaining_time":2.239946807},
{"learn":[0.2058291902],"iteration":384,"passed_time":1.399463602,"remaining_time":2.235506793},
{"learn":[0.2054261617],"iteration":385,"passed_time":1.402837217,"remaining_time":2.231456092},
{"learn":[0.2049866464],"iteration":386,"passed_time":1.40632112,"remaining_time":2.227583582},
{"learn":[0.2046248081],"iteration":387,"passed_time":1.410079136,"remaining_time":2.224145442},
{"learn":[0.2045225951],"iteration":388,"passed_time":1.41328705,"remaining_time":2.219841613},
{"learn":[0.2042458646],"iteration":389,"passed_time":1.416575127,"remaining_time":2.215668788},
{"learn":[0.2036324913],"iteration":390,"passed_time":1.420029281,"remaining_time":2.211759161},
{"learn":[0.2033825854],"iteration":391,"passed_time":1.423282192,"remaining_time":2.207539727},
{"learn":[0.2031146587],"iteration":392,"passed_time":1.427024751,"remaining_time":2.204081486},
{"learn":[0.2025791476],"iteration":393,"passed_time":1.430394741,"remaining_time":2.200048765},
{"learn":[0.2022448884],"iteration":394,"passed_time":1.433869269,"remaining_time":2.196179514},
{"learn":[0.2019854022],"iteration":395,"passed_time":1.437113015,"remaining_time":2.191960255},
{"learn":[0.2016869216],"iteration":396,"passed_time":1.440408925,"remaining_time":2.187825143},
{"learn":[0.2016220099],"iteration":397,"passed_time":1.443214938,"remaining_time":2.182953248},
{"learn":[0.2015609085],"iteration":398,"passed_time":1.44616182,"remaining_time":2.178303894},
{"learn":[0.2010659657],"iteration":399,"passed_time":1.449763385,"remaining_time":2.174645077},
{"learn":[0.2006422785],"iteration":400,"passed_time":1.452930675,"remaining_time":2.170337841},
{"learn":[0.2003115819],"iteration":401,"passed_time":1.455951762,"remaining_time":2.165818791},
{"learn":[0.1999903642],"iteration":402,"passed_time":1.459225423,"remaining_time":2.161681334},
{"learn":[0.1997576249],"iteration":403,"passed_time":1.46259083,"remaining_time":2.157683502},
{"learn":[0.1996845555],"iteration":404,"passed_time":1.465603293,"remaining_time":2.153170271},
{"learn":[0.1992974443],"iteration":405,"passed_time":1.468927994,"remaining_time":2.149121252},
{"learn":[0.1988760092],"iteration":406,"passed_time":1.471883751,"remaining_time":2.144538242},
{"learn":[0.1984358533],"iteration":407,"passed_time":1.475207952,"remaining_time":2.140497812},
{"learn":[0.1980271705],"iteration":408,"passed_time":1.478725769,"remaining_time":2.136740659},
{"learn":[0.197800937],"iteration":409,"passed_time":1.481622362,"remaining_time":2.132090716},
{"learn":[0.197478577],"iteration":410,"passed_time":1.485139222,"remaining_time":2.128338203},
{"learn":[0.1972481038],"iteration":411,"passed_time":1.488192016,"remaining_time":2.123924528},
{"learn":[0.1971634489],"iteration":412,"passed_time":1.491144982,"remaining_time":2.119375555},
{"learn":[0.1967938646],"iteration":413,"passed_time":1.494604135,"remaining_time":2.115550781},
{"learn":[0.1965018711],"iteration":414,"passed_time":1.497659305,"remaining_time":2.111158297},
{"learn":[0.1961583241],"iteration":415,"passed_time":1.50087026,"remaining_time":2.106990942},
{"learn":[0.1960599351],"iteration":416,"passed_time":1.503779269,"remaining_time":2.102406028},
{"learn":[0.1956250224],"iteration":417,"passed_time":1.506864604,"remaining_time":2.09807464},
{"learn":[0.1955793329],"iteration":418,"passed_time":1.510180388,"remaining_time":2.094068748},
{"learn":[0.1953042525],"iteration":419,"passed_time":1.513536879,"remaining_time":2.090122357},
{"learn":[0.1948990843],"iteration":420,"passed_time":1.516729585,"remaining_time":2.085953514},
{"learn":[0.1944635382],"iteration":421,"passed_time":1.519764089,"remaining_time":2.081572614},
{"learn":[0.19441974],"iteration":422,"passed_time":1.52322495,"remaining_time":2.07777966},
{"learn":[0.1943690931],"iteration":423,"passed_time":1.526437197,"remaining_time":2.073650532},
{"learn":[0.1943273064],"iteration":424,"passed_time":1.52948095,"remaining_time":2.069297756},
{"learn":[0.1941285646],"iteration":425,"passed_time":1.532537662,"remaining_time":2.064968586},
{"learn":[0.1939628569],"iteration":426,"passed_time":1.535575124,"remaining_time":2.060619545},
{"learn":[0.1937489711],"iteration":427,"passed_time":1.538530881,"remaining_time":2.056167439},
{"learn":[0.1936504005],"iteration":428,"passed_time":1.541561343,"remaining_time":2.051821741},
{"learn":[0.1932932139],"iteration":429,"passed_time":1.544994581,"remaining_time":2.048016072},
{"learn":[0.1931232617],"iteration":430,"passed_time":1.548283658,"remaining_time":2.044021813},
{"learn":[0.1928368891],"iteration":431,"passed_time":1.551408491,"remaining_time":2.039814868},
{"learn":[0.1925758246],"iteration":432,"passed_time":1.554911435,"remaining_time":2.036108045},
{"learn":[0.1925363698],"iteration":433,"passed_time":1.558016227,"remaining_time":2.031882914},
{"learn":[0.1923089574],"iteration":434,"passed_time":1.561176434,"remaining_time":2.027734909},
{"learn":[0.1922713164],"iteration":435,"passed_time":1.56421373,"remaining_time":2.023432439},
{"learn":[0.1918083625],"iteration":436,"passed_time":1.567420477,"remaining_time":2.019354069},
{"learn":[0.1915008941],"iteration":437,"passed_time":1.570911087,"remaining_time":2.015643906},
{"learn":[0.1913930527],"iteration":438,"passed_time":1.574109293,"remaining_time":2.011561078},
{"learn":[0.1913580466],"iteration":439,"passed_time":1.577131422,"remaining_time":2.007258174},
{"learn":[0.1912072398],"iteration":440,"passed_time":1.579830189,"remaining_time":2.002551192},
{"learn":[0.1908979384],"iteration":441,"passed_time":1.58314814,"remaining_time":1.998634982},
{"learn":[0.1906262417],"iteration":442,"passed_time":1.586665041,"remaining_time":1.994971621},
{"learn":[0.1905050366],"iteration":443,"passed_time":1.589914828,"remaining_time":1.990974424},
{"learn":[0.1900610599],"iteration":444,"passed_time":1.593517226,"remaining_time":1.98742036},
{"learn":[0.1897591306],"iteration":445,"passed_time":1.596714307,"remaining_time":1.983362614},
{"learn":[0.1895417678],"iteration":446,"passed_time":1.599976385,"remaining_time":1.979389129},
{"learn":[0.1890577724],"iteration":447,"passed_time":1.603310001,"remaining_time":1.975506966},
{"learn":[0.1890254409],"iteration":448,"passed_time":1.606236051,"remaining_time":1.971127092},
{"learn":[0.1887483276],"iteration":449,"passed_time":1.609243431,"remaining_time":1.966853083},
{"learn":[0.1884637477],"iteration":450,"passed_time":1.61235514,"remaining_time":1.96271169},
{"learn":[0.1881225326],"iteration":451,"passed_time":1.615571845,"remaining_time":1.958702148},
{"learn":[0.1876595906],"iteration":452,"passed_time":1.618918003,"remaining_time":1.954852423},
{"learn":[0.1875111987],"iteration":453,"passed_time":1.622119292,"remaining_time":1.95083069},
{"learn":[0.1873931711],"iteration":454,"passed_time":1.625495532,"remaining_time":1.947022121},
{"learn":[0.1873440664],"iteration":455,"passed_time":1.628495496,"remaining_time":1.942766556},
{"learn":[0.1869390697],"iteration":456,"passed_time":1.63179503,"remaining_time":1.938872432},
{"learn":[0.1866113559],"iteration":457,"passed_time":1.634925905,"remaining_time":1.934781312},
{"learn":[0.1861943908],"iteration":458,"passed_time":1.638445265,"remaining_time":1.931152262},
{"learn":[0.1859491589],"iteration":459,"passed_time":1.641578181,"remaining_time":1.927070039},
{"learn":[0.1856490209],"iteration":460,"passed_time":1.644976796,"remaining_time":1.923302587},
{"learn":[0.1853013506],"iteration":461,"passed_time":1.648246665,"remaining_time":1.919386809},
{"learn":[0.1852728023],"iteration":462,"passed_time":1.650790397,"remaining_time":1.914631626},
{"learn":[0.1849741791],"iteration":463,"passed_time":1.653668782,"remaining_time":1.910272558},
{"learn":[0.184571656],"iteration":464,"passed_time":1.657388925,"remaining_time":1.906888333},
{"learn":[0.1843956844],"iteration":465,"passed_time":1.660737583,"remaining_time":1.903076972},
{"learn":[0.1843788161],"iteration":466,"passed_time":1.663585344,"remaining_time":1.898695906},
{"learn":[0.1843629757],"iteration":467,"passed_time":1.666370441,"remaining_time":1.894250159},
{"learn":[0.184336062],"iteration":468,"passed_time":1.669410195,"remaining_time":1.890099815},
{"learn":[0.1840929048],"iteration":469,"passed_time":1.672523279,"remaining_time":1.886036889},
{"learn":[0.1838743166],"iteration":470,"passed_time":1.675720026,"remaining_time":1.882071961},
{"learn":[0.1837321804],"iteration":471,"passed_time":1.678904982,"remaining_time":1.878097099},
{"learn":[0.1835694268],"iteration":472,"passed_time":1.681978443,"remaining_time":1.874001351},
{"learn":[0.1832571558],"iteration":473,"passed_time":1.685406764,"remaining_time":1.870303709},
{"learn":[0.1832293495],"iteration":474,"passed_time":1.688186528,"remaining_time":1.865890373},
{"learn":[0.183209458],"iteration":475,"passed_time":1.690992916,"remaining_time":1.86151321},
{"learn":[0.1829364235],"iteration":476,"passed_time":1.694198455,"remaining_time":1.857580276},
{"learn":[0.1828781049],"iteration":477,"passed_time":1.69698501,"remaining_time":1.853192835},
{"learn":[0.1827534732],"iteration":478,"passed_time":1.699935559,"remaining_time":1.848990451},
{"learn":[0.1826865216],"iteration":479,"passed_time":1.702883608,"remaining_time":1.844790575},
{"learn":[0.1823848122],"iteration":480,"passed_time":1.705998817,"remaining_time":1.84077627},
{"learn":[0.1822215247],"iteration":481,"passed_time":1.709059028,"remaining_time":1.83670659},
{"learn":[0.1821941618],"iteration":482,"passed_time":1.711775669,"remaining_time":1.832273335},
{"learn":[0.1820283516],"iteration":483,"passed_time":1.71459014,"remaining_time":1.827951472},
{"learn":[0.1816769463],"iteration":484,"passed_time":1.717787054,"remaining_time":1.824041923},
{"learn":[0.1816019347],"iteration":485,"passed_time":1.720570818,"remaining_time":1.819698355},
{"learn":[0.1815935341],"iteration":486,"passed_time":1.723657236,"remaining_time":1.815680004},
{"learn":[0.1810027297],"iteration":487,"passed_time":1.726966854,"remaining_time":1.81189965},
{"learn":[0.1806485766],"iteration":488,"passed_time":1.730065314,"remaining_time":1.807900563},
{"learn":[0.180408484],"iteration":489,"passed_time":1.733330933,"remaining_time":1.804079134},
{"learn":[0.1802652374],"iteration":490,"passed_time":1.7364456,"remaining_time":1.800103484},
{"learn":[0.1802279469],"iteration":491,"passed_time":1.739566517,"remaining_time":1.796137786},
{"learn":[0.1802021474],"iteration":492,"passed_time":1.742220745,"remaining_time":1.791695573},
{"learn":[0.1800419414],"iteration":493,"passed_time":1.745456949,"remaining_time":1.787856713},
{"learn":[0.1797622957],"iteration":494,"passed_time":1.748887562,"remaining_time":1.784218624},
{"learn":[0.1795940579],"iteration":495,"passed_time":1.751771947,"remaining_time":1.780026333},
{"learn":[0.1793464078],"iteration":496,"passed_time":1.755572378,"remaining_time":1.776766411},
{"learn":[0.1793377556],"iteration":497,"passed_time":1.758377058,"remaining_time":1.772500568},
{"learn":[0.1792810203],"iteration":498,"passed_time":1.761118157,"remaining_time":1.768176746},
{"learn":[0.178962311],"iteration":499,"passed_time":1.765063582,"remaining_time":1.765063582},
{"learn":[0.1787067396],"iteration":500,"passed_time":1.768398074,"remaining_time":1.761338601},
{"learn":[0.1783484732],"iteration":501,"passed_time":1.77145216,"remaining_time":1.757337004},
{"learn":[0.1783073366],"iteration":502,"passed_time":1.774266131,"remaining_time":1.753101923},
{"learn":[0.1781143766],"iteration":503,"passed_time":1.777523543,"remaining_time":1.749308884},
{"learn":[0.1781079124],"iteration":504,"passed_time":1.78017252,"remaining_time":1.744921579},
{"learn":[0.1780587332],"iteration":505,"passed_time":1.783049031,"remaining_time":1.740763283},
{"learn":[0.1779945743],"iteration":506,"passed_time":1.786233153,"remaining_time":1.736909161},
{"learn":[0.1779692179],"iteration":507,"passed_time":1.789388902,"remaining_time":1.733030197},
{"learn":[0.177660289],"iteration":508,"passed_time":1.792556443,"remaining_time":1.729165448},
{"learn":[0.1775912419],"iteration":509,"passed_time":1.795508783,"remaining_time":1.725096674},
{"learn":[0.1772450654],"iteration":510,"passed_time":1.798740404,"remaining_time":1.721299525},
{"learn":[0.1769200625],"iteration":511,"passed_time":1.801741909,"remaining_time":1.717285257},
{"learn":[0.1769085989],"iteration":512,"passed_time":1.804467425,"remaining_time":1.713012936},
{"learn":[0.1765527786],"iteration":513,"passed_time":1.807579967,"remaining_time":1.709112576},
{"learn":[0.1763352199],"iteration":514,"passed_time":1.811094702,"remaining_time":1.70559404},
{"learn":[0.1760735657],"iteration":515,"passed_time":1.814254742,"remaining_time":1.70174282},
{"learn":[0.1758132602],"iteration":516,"passed_time":1.817277663,"remaining_time":1.697766173},
{"learn":[0.1756627666],"iteration":517,"passed_time":1.820432662,"remaining_time":1.693916107},
{"learn":[0.1756564879],"iteration":518,"passed_time":1.823451042,"remaining_time":1.689942102},
{"learn":[0.175535186],"iteration":519,"passed_time":1.826635456,"remaining_time":1.686125037},
{"learn":[0.1755291514],"iteration":520,"passed_time":1.829303516,"remaining_time":1.681835671},
{"learn":[0.1754572804],"iteration":521,"passed_time":1.832485806,"remaining_time":1.678023401},
{"learn":[0.1751522666],"iteration":522,"passed_time":1.836152909,"remaining_time":1.674655713},
{"learn":[0.1750975549],"iteration":523,"passed_time":1.83894509,"remaining_time":1.670492104},
{"learn":[0.1749099557],"iteration":524,"passed_time":1.842205418,"remaining_time":1.666757283},
{"learn":[0.1747590973],"iteration":525,"passed_time":1.845654947,"remaining_time":1.663194762},
{"learn":[0.1745211182],"iteration":526,"passed_time":1.848779363,"remaining_time":1.659340871},
{"learn":[0.1742835607],"iteration":527,"passed_time":1.852148354,"remaining_time":1.655708377},
{"learn":[0.1742202331],"iteration":528,"passed_time":1.855175858,"remaining_time":1.651772834},
{"learn":[0.1739551814],"iteration":529,"passed_time":1.858228403,"remaining_time":1.647862923},
{"learn":[0.1739451097],"iteration":530,"passed_time":1.860957377,"remaining_time":1.643670452},
{"learn":[0.1737400182],"iteration":531,"passed_time":1.864298369,"remaining_time":1.640021873},
{"learn":[0.1735242013],"iteration":532,"passed_time":1.867456784,"remaining_time":1.636214481},
{"learn":[0.1734095578],"iteration":533,"passed_time":1.870838149,"remaining_time":1.632604078},
{"learn":[0.1732308516],"iteration":534,"passed_time":1.873847821,"remaining_time":1.62867147},
{"learn":[0.1729998827],"iteration":535,"passed_time":1.877240185,"remaining_time":1.625073593},
{"learn":[0.1729778339],"iteration":536,"passed_time":1.880482139,"remaining_time":1.621346798},
{"learn":[0.172972214],"iteration":537,"passed_time":1.883306776,"remaining_time":1.61726344},
{"learn":[0.1728088378],"iteration":538,"passed_time":1.886690516,"remaining_time":1.613662946},
{"learn":[0.1726033279],"iteration":539,"passed_time":1.890229875,"remaining_time":1.610195819},
{"learn":[0.1725391695],"iteration":540,"passed_time":1.89321563,"remaining_time":1.606258733},
{"learn":[0.1723572044],"iteration":541,"passed_time":1.896617744,"remaining_time":1.602676987},
{"learn":[0.1722894797],"iteration":542,"passed_time":1.899543086,"remaining_time":1.598694641},
{"learn":[0.1720767102],"iteration":543,"passed_time":1.903071862,"remaining_time":1.595222002},
{"learn":[0.1719621023],"iteration":544,"passed_time":1.906196028,"remaining_time":1.591411363},
{"learn":[0.1719045202],"iteration":545,"passed_time":1.909085496,"remaining_time":1.587408087},
{"learn":[0.1716703175],"iteration":546,"passed_time":1.912243995,"remaining_time":1.583631682},
{"learn":[0.1714217377],"iteration":547,"passed_time":1.915240501,"remaining_time":1.579723917},
{"learn":[0.171090415],"iteration":548,"passed_time":1.918446081,"remaining_time":1.575991225},
{"learn":[0.1710094969],"iteration":549,"passed_time":1.921655619,"remaining_time":1.572263689},
{"learn":[0.1706825113],"iteration":550,"passed_time":1.924988111,"remaining_time":1.568638225},
{"learn":[0.1704980648],"iteration":551,"passed_time":1.927988283,"remaining_time":1.564744114},
{"learn":[0.1701873473],"iteration":552,"passed_time":1.931056952,"remaining_time":1.560908603},
{"learn":[0.1699957405],"iteration":553,"passed_time":1.934215909,"remaining_time":1.557148548},
{"learn":[0.169975274],"iteration":554,"passed_time":1.937199873,"remaining_time":1.553250349},
{"learn":[0.1699310102],"iteration":555,"passed_time":1.940055509,"remaining_time":1.549252961},
{"learn":[0.1696795418],"iteration":556,"passed_time":1.943020891,"remaining_time":1.545346956},
{"learn":[0.1694711419],"iteration":557,"passed_time":1.946174598,"remaining_time":1.541593499},
{"learn":[0.1691368166],"iteration":558,"passed_time":1.949292765,"remaining_time":1.537814149},
{"learn":[0.1689556048],"iteration":559,"passed_time":1.952719712,"remaining_time":1.534279774},
{"learn":[0.1685552718],"iteration":560,"passed_time":1.955797881,"remaining_time":1.530472851},
{"learn":[0.1682803174],"iteration":561,"passed_time":1.959246951,"remaining_time":1.526957588},
{"learn":[0.1679193224],"iteration":562,"passed_time":1.962548028,"remaining_time":1.523327688},
{"learn":[0.1676329463],"iteration":563,"passed_time":1.96577469,"remaining_time":1.519641427},
{"learn":[0.1675855348],"iteration":564,"passed_time":1.968765321,"remaining_time":1.51577507},
{"learn":[0.1673864453],"iteration":565,"passed_time":1.971935319,"remaining_time":1.512049344},
{"learn":[0.1670976504],"iteration":566,"passed_time":1.975137358,"remaining_time":1.508350046},
{"learn":[0.1669208341],"iteration":567,"passed_time":1.978304898,"remaining_time":1.504626261},
{"learn":[0.1666752391],"iteration":568,"passed_time":1.98163689,"remaining_time":1.501028998},
{"learn":[0.1666188753],"iteration":569,"passed_time":1.984482068,"remaining_time":1.49706542},
{"learn":[0.1664381403],"iteration":570,"passed_time":1.987962513,"remaining_time":1.493583044},
{"learn":[0.1663799212],"iteration":571,"passed_time":1.990891937,"remaining_time":1.489688373},
{"learn":[0.1663157466],"iteration":572,"passed_time":1.993965398,"remaining_time":1.485904406},
{"learn":[0.1661480622],"iteration":573,"passed_time":1.997128771,"remaining_time":1.482189646},
{"learn":[0.1659173637],"iteration":574,"passed_time":2.000397474,"remaining_time":1.478554655},
{"learn":[0.1656602404],"iteration":575,"passed_time":2.003625345,"remaining_time":1.474890879},
{"learn":[0.1654667456],"iteration":576,"passed_time":2.006689015,"remaining_time":1.471108238},
{"learn":[0.1654614947],"iteration":577,"passed_time":2.009451279,"remaining_time":1.467108027},
{"learn":[0.1652284766],"iteration":578,"passed_time":2.012969305,"remaining_time":1.463661619},
{"learn":[0.1652233543],"iteration":579,"passed_time":2.015510287,"remaining_time":1.459507449},
{"learn":[0.1651709523],"iteration":580,"passed_time":2.018669536,"remaining_time":1.455804708},
{"learn":[0.164936197],"iteration":581,"passed_time":2.021810786,"remaining_time":1.452090908},
{"learn":[0.1647314735],"iteration":582,"passed_time":2.025123528,"remaining_time":1.448501735},
{"learn":[0.1647195],"iteration":583,"passed_time":2.027952374,"remaining_time":1.444568814},
{"learn":[0.1645167325],"iteration":584,"passed_time":2.031165204,"remaining_time":1.440912067},
{"learn":[0.1644626887],"iteration":585,"passed_time":2.033937718,"remaining_time":1.43694576},
{"learn":[0.1642922895],"iteration":586,"passed_time":2.037244836,"remaining_time":1.433359654},
{"learn":[0.1640510581],"iteration":587,"passed_time":2.040440041,"remaining_time":1.429696083},
{"learn":[0.1640452309],"iteration":588,"passed_time":2.043183973,"remaining_time":1.425719207},
{"learn":[0.1638663455],"iteration":589,"passed_time":2.046205269,"remaining_time":1.421939255},
{"learn":[0.1635293055],"iteration":590,"passed_time":2.049263606,"remaining_time":1.418187504},
{"learn":[0.163425629],"iteration":591,"passed_time":2.052320025,"remaining_time":1.414436774},
{"learn":[0.1631896092],"iteration":592,"passed_time":2.055520356,"remaining_time":1.410787158},
{"learn":[0.1631783429],"iteration":593,"passed_time":2.058386116,"remaining_time":1.406910376},
{"learn":[0.1631707513],"iteration":594,"passed_time":2.06113759,"remaining_time":1.4029592},
{"learn":[0.1631306185],"iteration":595,"passed_time":2.063983059,"remaining_time":1.399075765},
{"learn":[0.1631202553],"iteration":596,"passed_time":2.067011605,"remaining_time":1.395319392},
{"learn":[0.1629297865],"iteration":597,"passed_time":2.070293932,"remaining_time":1.391736055},
{"learn":[0.1626875553],"iteration":598,"passed_time":2.073313562,"remaining_time":1.38797786},
{"learn":[0.1624591156],"iteration":599,"passed_time":2.076475602,"remaining_time":1.384317068},
{"learn":[0.1622141891],"iteration":600,"passed_time":2.07981801,"remaining_time":1.380777681},
{"learn":[0.1619790183],"iteration":601,"passed_time":2.082820057,"remaining_time":1.377013925},
{"learn":[0.1617928544],"iteration":602,"passed_time":2.086481994,"remaining_time":1.37368715},
{"learn":[0.1615796444],"iteration":603,"passed_time":2.08976153,"remaining_time":1.370108553},
{"learn":[0.1613681248],"iteration":604,"passed_time":2.093018025,"remaining_time":1.3665159},
{"learn":[0.1611945476],"iteration":605,"passed_time":2.095938283,"remaining_time":1.362705748},
{"learn":[0.1610418799],"iteration":606,"passed_time":2.0990502,"remaining_time":1.359022617},
{"learn":[0.1609183398],"iteration":607,"passed_time":2.102173367,"remaining_time":1.355348618},
{"learn":[0.1606396303],"iteration":608,"passed_time":2.105625104,"remaining_time":1.351887382},
{"learn":[0.1604349255],"iteration":609,"passed_time":2.10894093,"remaining_time":1.348339283},
{"learn":[0.1601618803],"iteration":610,"passed_time":2.112523412,"remaining_time":1.344961714},
{"learn":[0.1599694056],"iteration":611,"passed_time":2.115900277,"remaining_time":1.341453117},
{"learn":[0.1597679472],"iteration":612,"passed_time":2.11916598,"remaining_time":1.337874771},
{"learn":[0.1595870695],"iteration":613,"passed_time":2.122223816,"remaining_time":1.334166764},
{"learn":[0.1595438963],"iteration":614,"passed_time":2.125098535,"remaining_time":1.330346237},
{"learn":[0.159382103],"iteration":615,"passed_time":2.128729598,"remaining_time":1.327000269},
{"learn":[0.1592021461],"iteration":616,"passed_time":2.131991218,"remaining_time":1.323424046},
{"learn":[0.1589995594],"iteration":617,"passed_time":2.135373666,"remaining_time":1.319923528},
{"learn":[0.1588993709],"iteration":618,"passed_time":2.138620453,"remaining_time":1.316339891},
{"learn":[0.1587053578],"iteration":619,"passed_time":2.142036192,"remaining_time":1.312860892},
{"learn":[0.158535837],"iteration":620,"passed_time":2.145533135,"remaining_time":1.309431656},
{"learn":[0.1583209955],"iteration":621,"passed_time":2.148957332,"remaining_time":1.305957993},
{"learn":[0.1582403858],"iteration":622,"passed_time":2.151947463,"remaining_time":1.302221819},
{"learn":[0.1581535976],"iteration":623,"passed_time":2.155109878,"remaining_time":1.29859185},
{"learn":[0.1581486873],"iteration":624,"passed_time":2.157823395,"remaining_time":1.294694037},
{"learn":[0.1579923552],"iteration":625,"passed_time":2.160947853,"remaining_time":1.291045522},
{"learn":[0.1579180002],"iteration":626,"passed_time":2.163923026,"remaining_time":1.28730987},
{"learn":[0.1577566619],"iteration":627,"passed_time":2.167205853,"remaining_time":1.283758881},
{"learn":[0.1576890395],"iteration":628,"passed_time":2.170055656,"remaining_time":1.279953336},
{"learn":[0.157534241],"iteration":629,"passed_time":2.173591015,"remaining_time":1.276553453},
{"learn":[0.1573289784],"iteration":630,"passed_time":2.176714223,"remaining_time":1.272912121},
{"learn":[0.1571313272],"iteration":631,"passed_time":2.180209042,"remaining_time":1.269488809},
{"learn":[0.1570817187],"iteration":632,"passed_time":2.183230546,"remaining_time":1.265790854},
{"learn":[0.1569467341],"iteration":633,"passed_time":2.186477125,"remaining_time":1.262224965},
{"learn":[0.156685802],"iteration":634,"passed_time":2.189632624,"remaining_time":1.258607729},
{"learn":[0.1565741223],"iteration":635,"passed_time":2.192427929,"remaining_time":1.254785796},
{"learn":[0.1564035841],"iteration":636,"passed_time":2.195437934,"remaining_time":1.251089435},
{"learn":[0.1562818436],"iteration":637,"passed_time":2.198666263,"remaining_time":1.247519102},
{"learn":[0.1562778001],"iteration":638,"passed_time":2.201281784,"remaining_time":1.243603637},
{"learn":[0.1560705466],"iteration":639,"passed_time":2.204508738,"remaining_time":1.240036165},
{"learn":[0.155872454],"iteration":640,"passed_time":2.207765733,"remaining_time":1.236486581},
{"learn":[0.1558561578],"iteration":641,"passed_time":2.21067045,"remaining_time":1.232741466},
{"learn":[0.1556589901],"iteration":642,"passed_time":2.213905946,"remaining_time":1.229182617},
{"learn":[0.1555224455],"iteration":643,"passed_time":2.217194731,"remaining_time":1.22565423},
{"learn":[0.1554905877],"iteration":644,"passed_time":2.219990411,"remaining_time":1.221855188},
{"learn":[0.1553192196],"iteration":645,"passed_time":2.223330736,"remaining_time":1.21835771},
{"learn":[0.1551543172],"iteration":646,"passed_time":2.226310034,"remaining_time":1.214663743},
{"learn":[0.1550916747],"iteration":647,"passed_time":2.229468866,"remaining_time":1.211069508},
{"learn":[0.1549964007],"iteration":648,"passed_time":2.232885438,"remaining_time":1.207616007},
{"learn":[0.1548830348],"iteration":649,"passed_time":2.236030104,"remaining_time":1.20401621},
{"learn":[0.1546444675],"iteration":650,"passed_time":2.239149021,"remaining_time":1.200404007},
{"learn":[0.1543557385],"iteration":651,"passed_time":2.242574759,"remaining_time":1.19695708},
{"learn":[0.1543203799],"iteration":652,"passed_time":2.245486226,"remaining_time":1.193236938},
{"learn":[0.1543002495],"iteration":653,"passed_time":2.248841717,"remaining_time":1.189754181},
{"learn":[0.1542006787],"iteration":654,"passed_time":2.252014716,"remaining_time":1.18617569},
{"learn":[0.1540497656],"iteration":655,"passed_time":2.255218046,"remaining_time":1.182614341},
{"learn":[0.1539834497],"iteration":656,"passed_time":2.258349879,"remaining_time":1.179016756},
{"learn":[0.153917814],"iteration":657,"passed_time":2.261541502,"remaining_time":1.175451662},
{"learn":[0.1539138323],"iteration":658,"passed_time":2.264410179,"remaining_time":1.171720593},
{"learn":[0.1536897918],"iteration":659,"passed_time":2.26758626,"remaining_time":1.168150498},
{"learn":[0.1535604217],"iteration":660,"passed_time":2.270924877,"remaining_time":1.164664952},
{"learn":[0.1534389211],"iteration":661,"passed_time":2.273956506,"remaining_time":1.16102311},
{"learn":[0.1533872566],"iteration":662,"passed_time":2.276910846,"remaining_time":1.157343824},
{"learn":[0.1532910362],"iteration":663,"passed_time":2.280149967,"remaining_time":1.153810827},
{"learn":[0.1531184777],"iteration":664,"passed_time":2.283790363,"remaining_time":1.15048086},
{"learn":[0.1528394033],"iteration":665,"passed_time":2.28703615,"remaining_time":1.146952063},
{"learn":[0.1527083623],"iteration":666,"passed_time":2.289996157,"remaining_time":1.14328144},
{"learn":[0.1525340175],"iteration":667,"passed_time":2.29329015,"remaining_time":1.139778937},
{"learn":[0.1524946924],"iteration":668,"passed_time":2.296062331,"remaining_time":1.136018881},
{"learn":[0.1523786072],"iteration":669,"passed_time":2.299370491,"remaining_time":1.132525764},
{"learn":[0.1523480898],"iteration":670,"passed_time":2.302174795,"remaining_time":1.128786152},
{"learn":[0.152343971],"iteration":671,"passed_time":2.304896603,"remaining_time":1.125009056},
{"learn":[0.1522689337],"iteration":672,"passed_time":2.308129099,"remaining_time":1.121483232},
{"learn":[0.1520827222],"iteration":673,"passed_time":2.311476591,"remaining_time":1.1180139},
{"learn":[0.1519743763],"iteration":674,"passed_time":2.31473621,"remaining_time":1.11450262},
{"learn":[0.1518411436],"iteration":675,"passed_time":2.318003705,"remaining_time":1.110995859},
{"learn":[0.1516686292],"iteration":676,"passed_time":2.321423985,"remaining_time":1.107562699},
{"learn":[0.1515901189],"iteration":677,"passed_time":2.324650731,"remaining_time":1.104037663},
{"learn":[0.1514219267],"iteration":678,"passed_time":2.327716484,"remaining_time":1.100437395},
{"learn":[0.1513944603],"iteration":679,"passed_time":2.330438042,"remaining_time":1.096676725},
{"learn":[0.1510903292],"iteration":680,"passed_time":2.333749701,"remaining_time":1.093195528},
{"learn":[0.1509275237],"iteration":681,"passed_time":2.336987488,"remaining_time":1.089680383},
{"learn":[0.1508351214],"iteration":682,"passed_time":2.340234734,"remaining_time":1.08617044},
{"learn":[0.1506859451],"iteration":683,"passed_time":2.343520061,"remaining_time":1.082678858},
{"learn":[0.1504749462],"iteration":684,"passed_time":2.347124,"remaining_time":1.079334394},
{"learn":[0.1503320292],"iteration":685,"passed_time":2.35050274,"remaining_time":1.075886094},
{"learn":[0.1502171618],"iteration":686,"passed_time":2.353408457,"remaining_time":1.072222485},
{"learn":[0.1500974608],"iteration":687,"passed_time":2.356438795,"remaining_time":1.068617593},
{"learn":[0.1499353851],"iteration":688,"passed_time":2.359665832,"remaining_time":1.065103155},
{"learn":[0.149913107],"iteration":689,"passed_time":2.362603882,"remaining_time":1.061459715},
{"learn":[0.1497695544],"iteration":690,"passed_time":2.365882459,"remaining_time":1.057970593},
{"learn":[0.1496805174],"iteration":691,"passed_time":2.369060749,"remaining_time":1.054437443},
{"learn":[0.1495918704],"iteration":692,"passed_time":2.372273121,"remaining_time":1.050920416},
{"learn":[0.1495677611],"iteration":693,"passed_time":2.375021136,"remaining_time":1.047199521},
{"learn":[0.1493338346],"iteration":694,"passed_time":2.37830663,"remaining_time":1.043717298},
{"learn":[0.1493236674],"iteration":695,"passed_time":2.381300135,"remaining_time":1.040108105},
{"learn":[0.149206199],"iteration":696,"passed_time":2.384251684,"remaining_time":1.036482439},
{"learn":[0.1491462731],"iteration":697,"passed_time":2.387046155,"remaining_time":1.032790743},
{"learn":[0.1490198921],"iteration":698,"passed_time":2.390101742,"remaining_time":1.029214055},
{"learn":[0.1488536429],"iteration":699,"passed_time":2.393460816,"remaining_time":1.025768921},
{"learn":[0.1487402119],"iteration":700,"passed_time":2.396591358,"remaining_time":1.022226556},
{"learn":[0.1485137143],"iteration":701,"passed_time":2.40012505,"remaining_time":1.018856503},
{"learn":[0.1483693627],"iteration":702,"passed_time":2.40354258,"remaining_time":1.015436908},
{"learn":[0.1483108462],"iteration":703,"passed_time":2.406584042,"remaining_time":1.011859199},
{"learn":[0.1482920725],"iteration":704,"passed_time":2.409466385,"remaining_time":1.008216431},
{"learn":[0.1482233265],"iteration":705,"passed_time":2.413003619,"remaining_time":1.004848532},
{"learn":[0.1479349192],"iteration":706,"passed_time":2.416313153,"remaining_time":1.00138579},
{"learn":[0.1478537263],"iteration":707,"passed_time":2.419508109,"remaining_time":0.9978762257},
{"learn":[0.1478403315],"iteration":708,"passed_time":2.422630359,"remaining_time":0.9943377073},
{"learn":[0.147730208],"iteration":709,"passed_time":2.425680196,"remaining_time":0.9907707841},
{"learn":[0.1477263833],"iteration":710,"passed_time":2.428619537,"remaining_time":0.9871604023},
{"learn":[0.1475550051],"iteration":711,"passed_time":2.431800493,"remaining_time":0.9836496376},
{"learn":[0.1473581279],"iteration":712,"passed_time":2.435324977,"remaining_time":0.9802780763},
{"learn":[0.1472194778],"iteration":713,"passed_time":2.438440853,"remaining_time":0.9767424144},
{"learn":[0.1471465201],"iteration":714,"passed_time":2.441559103,"remaining_time":0.9732088733},
{"learn":[0.1469842052],"iteration":715,"passed_time":2.444740684,"remaining_time":0.9697016122},
{"learn":[0.1467986297],"iteration":716,"passed_time":2.448075468,"remaining_time":0.9662557286},
{"learn":[0.1466080322],"iteration":717,"passed_time":2.451089014,"remaining_time":0.962683986},
{"learn":[0.1465346248],"iteration":718,"passed_time":2.454073228,"remaining_time":0.9591023326},
{"learn":[0.1465216728],"iteration":719,"passed_time":2.4568632,"remaining_time":0.9554468},
{"learn":[0.146350942],"iteration":720,"passed_time":2.459864247,"remaining_time":0.9518753466},
{"learn":[0.1462433318],"iteration":721,"passed_time":2.46326032,"remaining_time":0.9484575746},
{"learn":[0.1461245734],"iteration":722,"passed_time":2.466543438,"remaining_time":0.9449965871},
{"learn":[0.1458992787],"iteration":723,"passed_time":2.469602858,"remaining_time":0.9414508132},
{"learn":[0.1457080917],"iteration":724,"passed_time":2.47271165,"remaining_time":0.9379251088},
{"learn":[0.1455722694],"iteration":725,"passed_time":2.476120431,"remaining_time":0.9345137715},
{"learn":[0.145375039],"iteration":726,"passed_time":2.479370801,"remaining_time":0.9310429556},
{"learn":[0.1453475137],"iteration":727,"passed_time":2.482162231,"remaining_time":0.9274012732},
{"learn":[0.1451870756],"iteration":728,"passed_time":2.48557097,"remaining_time":0.9239914032},
{"learn":[0.1451503828],"iteration":729,"passed_time":2.488511311,"remaining_time":0.9204082931},
{"learn":[0.1450315331],"iteration":730,"passed_time":2.491894009,"remaining_time":0.9169897243},
{"learn":[0.1449687622],"iteration":731,"passed_time":2.494981261,"remaining_time":0.9134630846},
{"learn":[0.1449124904],"iteration":732,"passed_time":2.498398499,"remaining_time":0.9100578436},
{"learn":[0.1449040782],"iteration":733,"passed_time":2.501285342,"remaining_time":0.9064603557},
{"learn":[0.1448893617],"iteration":734,"passed_time":2.504209517,"remaining_time":0.9028782613},
{"learn":[0.1447333944],"iteration":735,"passed_time":2.50757555,"remaining_time":0.8994564471},
{"learn":[0.14458917],"iteration":736,"passed_time":2.510915499,"remaining_time":0.8960254767},
{"learn":[0.144452772],"iteration":737,"passed_time":2.513953503,"remaining_time":0.892487558},
{"learn":[0.1443140808],"iteration":738,"passed_time":2.517051588,"remaining_time":0.8889722116},
{"learn":[0.1442988131],"iteration":739,"passed_time":2.520173671,"remaining_time":0.8854664251},
{"learn":[0.1442901154],"iteration":740,"passed_time":2.523221008,"remaining_time":0.881935548},
{"learn":[0.1442485631],"iteration":741,"passed_time":2.526260928,"remaining_time":0.8784033955},
{"learn":[0.1440994109],"iteration":742,"passed_time":2.529723498,"remaining_time":0.8750187605},
{"learn":[0.1440645207],"iteration":743,"passed_time":2.532752169,"remaining_time":0.8714846173},
{"learn":[0.1440611568],"iteration":744,"passed_time":2.535553557,"remaining_time":0.8678740363},
{"learn":[0.143936732],"iteration":745,"passed_time":2.538755304,"remaining_time":0.86440194},
{"learn":[0.1438817436],"iteration":746,"passed_time":2.541998425,"remaining_time":0.8609445802},
{"learn":[0.1438780884],"iteration":747,"passed_time":2.544586488,"remaining_time":0.8572671055},
{"learn":[0.1438745375],"iteration":748,"passed_time":2.547539245,"remaining_time":0.8537147537},
{"learn":[0.1436981609],"iteration":749,"passed_time":2.550922443,"remaining_time":0.8503074811},
{"learn":[0.1434683176],"iteration":750,"passed_time":2.553968738,"remaining_time":0.8467885696},
{"learn":[0.1434535237],"iteration":751,"passed_time":2.557014366,"remaining_time":0.8432706953},
{"learn":[0.143263601],"iteration":752,"passed_time":2.560118034,"remaining_time":0.8397731135},
{"learn":[0.1432388424],"iteration":753,"passed_time":2.563235243,"remaining_time":0.8362809944},
{"learn":[0.1431442605],"iteration":754,"passed_time":2.566539653,"remaining_time":0.8328506158},
{"learn":[0.1430465442],"iteration":755,"passed_time":2.570044596,"remaining_time":0.8294852929},
{"learn":[0.1428937989],"iteration":756,"passed_time":2.573354047,"remaining_time":0.8260568474},
{"learn":[0.1427922668],"iteration":757,"passed_time":2.576593418,"remaining_time":0.8226063418},
{"learn":[0.1427578403],"iteration":758,"passed_time":2.579610172,"remaining_time":0.8190857069},
{"learn":[0.1426112259],"iteration":759,"passed_time":2.58292504,"remaining_time":0.8156605389},
{"learn":[0.1424542062],"iteration":760,"passed_time":2.58608458,"remaining_time":0.8121868787},
{"learn":[0.1423610563],"iteration":761,"passed_time":2.589131667,"remaining_time":0.8086789196},
{"learn":[0.1423406815],"iteration":762,"passed_time":2.59181906,"remaining_time":0.8050604419},
{"learn":[0.1422310634],"iteration":763,"passed_time":2.595450081,"remaining_time":0.801735889},
{"learn":[0.1421328119],"iteration":764,"passed_time":2.598899027,"remaining_time":0.798354603},
{"learn":[0.1419941248],"iteration":765,"passed_time":2.602116148,"remaining_time":0.7949023221},
{"learn":[0.1419798874],"iteration":766,"passed_time":2.604887538,"remaining_time":0.7913152494},
{"learn":[0.1419661997],"iteration":767,"passed_time":2.60808341,"remaining_time":0.7878585301},
{"learn":[0.1419202048],"iteration":768,"passed_time":2.611215827,"remaining_time":0.7843834277},
{"learn":[0.1417455665],"iteration":769,"passed_time":2.614393866,"remaining_time":0.7809228432},
{"learn":[0.1417230349],"iteration":770,"passed_time":2.617367456,"remaining_time":0.7774022664},
{"learn":[0.1416112961],"iteration":771,"passed_time":2.620715905,"remaining_time":0.7739938166},
{"learn":[0.1415891692],"iteration":772,"passed_time":2.623758534,"remaining_time":0.7704957144},
{"learn":[0.1415710625],"iteration":773,"passed_time":2.626547048,"remaining_time":0.7669245901},
{"learn":[0.1414929607],"iteration":774,"passed_time":2.629855707,"remaining_time":0.7635064956},
{"learn":[0.1414518751],"iteration":775,"passed_time":2.632798964,"remaining_time":0.7599832062},
{"learn":[0.1414483913],"iteration":776,"passed_time":2.635439442,"remaining_time":0.7563745118},
{"learn":[0.1412620022],"iteration":777,"passed_time":2.638639273,"remaining_time":0.7529279159},
{"learn":[0.1411413017],"iteration":778,"passed_time":2.641883643,"remaining_time":0.7494945894},
{"learn":[0.1411356631],"iteration":779,"passed_time":2.644742071,"remaining_time":0.7459528918},
{"learn":[0.1409578895],"iteration":780,"passed_time":2.64767712,"remaining_time":0.7424344294},
{"learn":[0.1408632081],"iteration":781,"passed_time":2.650841119,"remaining_time":0.7389812838},
{"learn":[0.1406883153],"iteration":782,"passed_time":2.654104863,"remaining_time":0.7355565203},
{"learn":[0.1406383454],"iteration":783,"passed_time":2.657028913,"remaining_time":0.7320385782},
{"learn":[0.1406350709],"iteration":784,"passed_time":2.659709806,"remaining_time":0.728455552},
{"learn":[0.1406157301],"iteration":785,"passed_time":2.662903012,"remaining_time":0.7250143061},
{"learn":[0.1406125583],"iteration":786,"passed_time":2.666097968,"remaining_time":0.7215741641},
{"learn":[0.1404354159],"iteration":787,"passed_time":2.670312508,"remaining_time":0.7184089488},
{"learn":[0.1403897819],"iteration":788,"passed_time":2.674160354,"remaining_time":0.7151430098},
{"learn":[0.1403752989],"iteration":789,"passed_time":2.678579178,"remaining_time":0.7120273763},
{"learn":[0.1402562092],"iteration":790,"passed_time":2.681797757,"remaining_time":0.7085913164},
{"learn":[0.1402121993],"iteration":791,"passed_time":2.684671434,"remaining_time":0.7050652251},
{"learn":[0.1400733219],"iteration":792,"passed_time":2.687656273,"remaining_time":0.7015697964},
{"learn":[0.1399869083],"iteration":793,"passed_time":2.691043721,"remaining_time":0.6981801091},
{"learn":[0.1398400405],"iteration":794,"passed_time":2.694028519,"remaining_time":0.6946865992},
{"learn":[0.1397319758],"iteration":795,"passed_time":2.697052148,"remaining_time":0.6912043193},
{"learn":[0.1397286299],"iteration":796,"passed_time":2.69971175,"remaining_time":0.6876304709},
{"learn":[0.1396677955],"iteration":797,"passed_time":2.702601135,"remaining_time":0.6841170792},
{"learn":[0.1395624957],"iteration":798,"passed_time":2.705831256,"remaining_time":0.6806909667},
{"learn":[0.1394449226],"iteration":799,"passed_time":2.709361948,"remaining_time":0.677340487},
{"learn":[0.1394416499],"iteration":800,"passed_time":2.712108297,"remaining_time":0.6737946954},
{"learn":[0.1394118877],"iteration":801,"passed_time":2.71506072,"remaining_time":0.6703017739},
{"learn":[0.1392497466],"iteration":802,"passed_time":2.718383796,"remaining_time":0.6669011305},
{"learn":[0.139212004],"iteration":803,"passed_time":2.721167268,"remaining_time":0.663369135},
{"learn":[0.1392088078],"iteration":804,"passed_time":2.724074777,"remaining_time":0.6598690454},
{"learn":[0.1391592625],"iteration":805,"passed_time":2.727400019,"remaining_time":0.6564709724},
{"learn":[0.1390452767],"iteration":806,"passed_time":2.730797758,"remaining_time":0.6530904181},
{"learn":[0.1389345131],"iteration":807,"passed_time":2.734086544,"remaining_time":0.6496839312},
{"learn":[0.1389214358],"iteration":808,"passed_time":2.737244751,"remaining_time":0.6462469066},
{"learn":[0.1388727794],"iteration":809,"passed_time":2.740920979,"remaining_time":0.6429320815},
{"learn":[0.1387463004],"iteration":810,"passed_time":2.7447842,"remaining_time":0.639659943},
{"learn":[0.1386489593],"iteration":811,"passed_time":2.748141649,"remaining_time":0.6362692488},
{"learn":[0.1386411693],"iteration":812,"passed_time":2.750672048,"remaining_time":0.6326884046},
{"learn":[0.138614131],"iteration":813,"passed_time":2.753575182,"remaining_time":0.6291953119},
{"learn":[0.1385142006],"iteration":814,"passed_time":2.756813886,"remaining_time":0.6257798392},
{"learn":[0.1384970756],"iteration":815,"passed_time":2.759731936,"remaining_time":0.6222924954},
{"learn":[0.1384939411],"iteration":816,"passed_time":2.762575989,"remaining_time":0.6187899707},
{"learn":[0.1383819356],"iteration":817,"passed_time":2.765998977,"remaining_time":0.6154178654},
{"learn":[0.1382713558],"iteration":818,"passed_time":2.769238931,"remaining_time":0.6120051851},
{"learn":[0.138233488],"iteration":819,"passed_time":2.772069402,"remaining_time":0.6085030394},
{"learn":[0.1381345621],"iteration":820,"passed_time":2.775318314,"remaining_time":0.6050937614},
{"learn":[0.1381114129],"iteration":821,"passed_time":2.77811341,"remaining_time":0.6015866022},
{"learn":[0.1379544997],"iteration":822,"passed_time":2.781527982,"remaining_time":0.598214402},
{"learn":[0.137951406],"iteration":823,"passed_time":2.784429991,"remaining_time":0.5947326195},
{"learn":[0.1378613117],"iteration":824,"passed_time":2.787752817,"remaining_time":0.5913415066},
{"learn":[0.1378582572],"iteration":825,"passed_time":2.790494624,"remaining_time":0.5878281654},
{"learn":[0.1377743498],"iteration":826,"passed_time":2.793619666,"remaining_time":0.5843968588},
{"learn":[0.1376903025],"iteration":827,"passed_time":2.796841954,"remaining_time":0.5809864928},
{"learn":[0.1375793721],"iteration":828,"passed_time":2.800133864,"remaining_time":0.5775909418},
{"learn":[0.1375000388],"iteration":829,"passed_time":2.803322362,"remaining_time":0.5741744596},
{"learn":[0.1372621459],"iteration":830,"passed_time":2.806436404,"remaining_time":0.5707433842},
{"learn":[0.1372271762],"iteration":831,"passed_time":2.809835893,"remaining_time":0.5673707092},
{"learn":[0.1371012712],"iteration":832,"passed_time":2.81305089,"remaining_time":0.5639609827},
{"learn":[0.1369755669],"iteration":833,"passed_time":2.816180265,"remaining_time":0.560534681},
{"learn":[0.1368378904],"iteration":834,"passed_time":2.819135105,"remaining_time":0.5570746016},
{"learn":[0.1367349555],"iteration":835,"passed_time":2.822370059,"remaining_time":0.5536706815},
{"learn":[0.1367224012],"iteration":836,"passed_time":2.825622763,"remaining_time":0.5502706216},
{"learn":[0.1367077332],"iteration":837,"passed_time":2.828453066,"remaining_time":0.5467892562},
{"learn":[0.1366730479],"iteration":838,"passed_time":2.831233622,"remaining_time":0.5432998964},
{"learn":[0.1365663515],"iteration":839,"passed_time":2.834584113,"remaining_time":0.5399207834},
{"learn":[0.1364377317],"iteration":840,"passed_time":2.837887564,"remaining_time":0.5365328451},
{"learn":[0.136319674],"iteration":841,"passed_time":2.840950484,"remaining_time":0.533099972},
{"learn":[0.1361784999],"iteration":842,"passed_time":2.844048027,"remaining_time":0.5296744249},
{"learn":[0.1360318754],"iteration":843,"passed_time":2.847458015,"remaining_time":0.5263074057},
{"learn":[0.1359936903],"iteration":844,"passed_time":2.850434897,"remaining_time":0.522860839},
{"learn":[0.1358691984],"iteration":845,"passed_time":2.853607936,"remaining_time":0.5194510901},
{"learn":[0.1357684895],"iteration":846,"passed_time":2.856723479,"remaining_time":0.5160315139},
{"learn":[0.135685874],"iteration":847,"passed_time":2.860043304,"remaining_time":0.5126492715},
{"learn":[0.1356827879],"iteration":848,"passed_time":2.862914315,"remaining_time":0.5091873516},
{"learn":[0.1356131382],"iteration":849,"passed_time":2.866165518,"remaining_time":0.505793915},
{"learn":[0.1354420474],"iteration":850,"passed_time":2.869298643,"remaining_time":0.5023801384},
{"learn":[0.1352679155],"iteration":851,"passed_time":2.872399186,"remaining_time":0.4989613609},
{"learn":[0.1352648989],"iteration":852,"passed_time":2.875304278,"remaining_time":0.495509647},
{"learn":[0.1351214737],"iteration":853,"passed_time":2.878682018,"remaining_time":0.4921400172},
{"learn":[0.135018968],"iteration":854,"passed_time":2.88219267,"remaining_time":0.4887929089},
{"learn":[0.1349661958],"iteration":855,"passed_time":2.885302587,"remaining_time":0.4853780053},
{"learn":[0.1349417289],"iteration":856,"passed_time":2.888077393,"remaining_time":0.4819078964},
{"learn":[0.1347700067],"iteration":857,"passed_time":2.891192727,"remaining_time":0.478495766},
{"learn":[0.1346890254],"iteration":858,"passed_time":2.894233355,"remaining_time":0.4750720642},
{"learn":[0.134657062],"iteration":859,"passed_time":2.896952789,"remaining_time":0.4715969656},
{"learn":[0.1345246157],"iteration":860,"passed_time":2.900553853,"remaining_time":0.468265953},
{"learn":[0.134468294],"iteration":861,"passed_time":2.903693686,"remaining_time":0.4648604741},
{"learn":[0.1342824223],"iteration":862,"passed_time":2.906790396,"remaining_time":0.461448765},
{"learn":[0.134238041],"iteration":863,"passed_time":2.91010293,"remaining_time":0.4580717575},
{"learn":[0.1341384897],"iteration":864,"passed_time":2.913472879,"remaining_time":0.4547038597},
{"learn":[0.1341357593],"iteration":865,"passed_time":2.916525715,"remaining_time":0.4512868889},
{"learn":[0.134087939],"iteration":866,"passed_time":2.919682714,"remaining_time":0.447886737},
{"learn":[0.1340671484],"iteration":867,"passed_time":2.922423229,"remaining_time":0.4444238091},
{"learn":[0.1340029887],"iteration":868,"passed_time":2.925471524,"remaining_time":0.441008941},
{"learn":[0.1337967829],"iteration":869,"passed_time":2.928981551,"remaining_time":0.4376639099},
{"learn":[0.1337192085],"iteration":870,"passed_time":2.931952057,"remaining_time":0.434238594},
{"learn":[0.1335452274],"iteration":871,"passed_time":2.935443293,"remaining_time":0.4308907586},
{"learn":[0.1333690055],"iteration":872,"passed_time":2.938663706,"remaining_time":0.4275031966},
{"learn":[0.1331666673],"iteration":873,"passed_time":2.942405098,"remaining_time":0.424191124},
{"learn":[0.1331447349],"iteration":874,"passed_time":2.945361605,"remaining_time":0.4207659436},
{"learn":[0.1331252114],"iteration":875,"passed_time":2.948140286,"remaining_time":0.4173166614},
{"learn":[0.1330370828],"iteration":876,"passed_time":2.951423113,"remaining_time":0.4139396156},
{"learn":[0.1330020156],"iteration":877,"passed_time":2.954505656,"remaining_time":0.4105349545},
{"learn":[0.1329756914],"iteration":878,"passed_time":2.957603033,"remaining_time":0.4071330682},
{"learn":[0.1328827429],"iteration":879,"passed_time":2.960927858,"remaining_time":0.4037628898},
{"learn":[0.1327986628],"iteration":880,"passed_time":2.96418627,"remaining_time":0.4003838435},
{"learn":[0.1327394508],"iteration":881,"passed_time":2.96734456,"remaining_time":0.3969916759},
{"learn":[0.1327097149],"iteration":882,"passed_time":2.970317566,"remaining_time":0.3935754873},
{"learn":[0.1326092553],"iteration":883,"passed_time":2.973179785,"remaining_time":0.3901457637},
{"learn":[0.1326063587],"iteration":884,"passed_time":2.975926967,"remaining_time":0.3867023743},
{"learn":[0.1325396734],"iteration":885,"passed_time":2.979091841,"remaining_time":0.3833143001},
{"learn":[0.1324408546],"iteration":886,"passed_time":2.982530204,"remaining_time":0.3799615705},
{"learn":[0.1323458801],"iteration":887,"passed_time":2.985516043,"remaining_time":0.376551573},
{"learn":[0.132172828],"iteration":888,"passed_time":2.989005487,"remaining_time":0.3732054095},
{"learn":[0.1321699718],"iteration":889,"passed_time":2.991637257,"remaining_time":0.3697529194},
{"learn":[0.1321672079],"iteration":890,"passed_time":2.994428812,"remaining_time":0.3663218187},
{"learn":[0.1320371891],"iteration":891,"passed_time":2.99756727,"remaining_time":0.3629341537},
{"learn":[0.1320307676],"iteration":892,"passed_time":3.00038799,"remaining_time":0.3595089753},
{"learn":[0.131976702],"iteration":893,"passed_time":3.003758897,"remaining_time":0.3561503838},
{"learn":[0.1318438506],"iteration":894,"passed_time":3.007419585,"remaining_time":0.3528257613},
{"learn":[0.1317041271],"iteration":895,"passed_time":3.010588875,"remaining_time":0.3494433515},
{"learn":[0.1316077427],"iteration":896,"passed_time":3.013811954,"remaining_time":0.3460675934},
{"learn":[0.1315845441],"iteration":897,"passed_time":3.016786835,"remaining_time":0.3426639835},
{"learn":[0.1314577853],"iteration":898,"passed_time":3.020317361,"remaining_time":0.3393237525},
{"learn":[0.1314547421],"iteration":899,"passed_time":3.023065918,"remaining_time":0.3358962131},
{"learn":[0.1314517807],"iteration":900,"passed_time":3.026140295,"remaining_time":0.3325059814},
{"learn":[0.1314491366],"iteration":901,"passed_time":3.02886202,"remaining_time":0.3290781352},
{"learn":[0.131393886],"iteration":902,"passed_time":3.031876858,"remaining_time":0.3256833391},
{"learn":[0.1313717806],"iteration":903,"passed_time":3.034937277,"remaining_time":0.3222942241},
{"learn":[0.1313689296],"iteration":904,"passed_time":3.037547964,"remaining_time":0.3188586261},
{"learn":[0.1312328656],"iteration":905,"passed_time":3.040643174,"remaining_time":0.3154751196},
{"learn":[0.1312300794],"iteration":906,"passed_time":3.043243862,"remaining_time":0.3120415426},
{"learn":[0.131227391],"iteration":907,"passed_time":3.046099956,"remaining_time":0.3086356784},
{"learn":[0.1311472711],"iteration":908,"passed_time":3.049241581,"remaining_time":0.3052596082},
{"learn":[0.1311445992],"iteration":909,"passed_time":3.051951472,"remaining_time":0.3018413544},
{"learn":[0.1311419925],"iteration":910,"passed_time":3.054575034,"remaining_time":0.2984162218},
{"learn":[0.131139443],"iteration":911,"passed_time":3.057364173,"remaining_time":0.2950088237},
{"learn":[0.1311369687],"iteration":912,"passed_time":3.060019525,"remaining_time":0.2915900314},
{"learn":[0.1311101743],"iteration":913,"passed_time":3.062840663,"remaining_time":0.2881885087},
{"learn":[0.1310577053],"iteration":914,"passed_time":3.065750255,"remaining_time":0.2847964717},
{"learn":[0.131055356],"iteration":915,"passed_time":3.068431481,"remaining_time":0.2813845463},
{"learn":[0.1309205722],"iteration":916,"passed_time":3.071572522,"remaining_time":0.2780158335},
{"learn":[0.1309182297],"iteration":917,"passed_time":3.07443195,"remaining_time":0.2746224617},
{"learn":[0.1308976525],"iteration":918,"passed_time":3.077406081,"remaining_time":0.2712403619},
{"learn":[0.1308297578],"iteration":919,"passed_time":3.080567204,"remaining_time":0.2678754091},
{"learn":[0.1307880881],"iteration":920,"passed_time":3.083493671,"remaining_time":0.2644907709},
{"learn":[0.1306257473],"iteration":921,"passed_time":3.086446678,"remaining_time":0.2611093719},
{"learn":[0.1306234813],"iteration":922,"passed_time":3.089063823,"remaining_time":0.2577008823},
{"learn":[0.1304889686],"iteration":923,"passed_time":3.092424814,"remaining_time":0.2543552877},
{"learn":[0.1304659299],"iteration":924,"passed_time":3.095634894,"remaining_time":0.2509974239},
{"learn":[0.1304504938],"iteration":925,"passed_time":3.098468656,"remaining_time":0.2476098062},
{"learn":[0.1303827094],"iteration":926,"passed_time":3.101419205,"remaining_time":0.2442325803},
{"learn":[0.1303804942],"iteration":927,"passed_time":3.104136971,"remaining_time":0.2408382133},
{"learn":[0.1303745179],"iteration":928,"passed_time":3.107226723,"remaining_time":0.2374737323},
{"learn":[0.1303521153],"iteration":929,"passed_time":3.110391097,"remaining_time":0.2341154589},
{"learn":[0.1302330768],"iteration":930,"passed_time":3.113571178,"remaining_time":0.2307587661},
{"learn":[0.1301202387],"iteration":931,"passed_time":3.116876629,"remaining_time":0.2274115996},
{"learn":[0.1300114597],"iteration":932,"passed_time":3.120186205,"remaining_time":0.2240648186},
{"learn":[0.12991051],"iteration":933,"passed_time":3.123362037,"remaining_time":0.2207086664},
{"learn":[0.1298752235],"iteration":934,"passed_time":3.126640323,"remaining_time":0.2173600224},
{"learn":[0.1298327077],"iteration":935,"passed_time":3.129561039,"remaining_time":0.2139870796},
{"learn":[0.1298305079],"iteration":936,"passed_time":3.132316762,"remaining_time":0.2106040086},
{"learn":[0.1298065633],"iteration":937,"passed_time":3.134970115,"remaining_time":0.2072155087},
{"learn":[0.1297458703],"iteration":938,"passed_time":3.138243234,"remaining_time":0.2038688363},
{"learn":[0.129729509],"iteration":939,"passed_time":3.141085079,"remaining_time":0.2004947923},
{"learn":[0.1297083112],"iteration":940,"passed_time":3.144421779,"remaining_time":0.1971529064},
{"learn":[0.1296919512],"iteration":941,"passed_time":3.147196501,"remaining_time":0.19377643},
{"learn":[0.1295808646],"iteration":942,"passed_time":3.150205506,"remaining_time":0.1904153912},
{"learn":[0.1294570209],"iteration":943,"passed_time":3.153556122,"remaining_time":0.1870753632},
{"learn":[0.1294548961],"iteration":944,"passed_time":3.156302804,"remaining_time":0.1837001632},
{"learn":[0.1294326489],"iteration":945,"passed_time":3.159396139,"remaining_time":0.1803460798},
{"learn":[0.1293154578],"iteration":946,"passed_time":3.162846918,"remaining_time":0.1770125519},
{"learn":[0.1292491631],"iteration":947,"passed_time":3.166063956,"remaining_time":0.1736659554},
{"learn":[0.1291683134],"iteration":948,"passed_time":3.168970298,"remaining_time":0.1703029349},
{"learn":[0.129066848],"iteration":949,"passed_time":3.172148921,"remaining_time":0.1669552064},
{"learn":[0.1289898434],"iteration":950,"passed_time":3.175356668,"remaining_time":0.1636093341},
{"learn":[0.1289876005],"iteration":951,"passed_time":3.177855235,"remaining_time":0.1602279951},
{"learn":[0.1289700406],"iteration":952,"passed_time":3.180878989,"remaining_time":0.1568744098},
{"learn":[0.1289129162],"iteration":953,"passed_time":3.18403053,"remaining_time":0.1535276776},
{"learn":[0.1288298241],"iteration":954,"passed_time":3.187437769,"remaining_time":0.1501934027},
{"learn":[0.1287562193],"iteration":955,"passed_time":3.190667223,"remaining_time":0.1468507927},
{"learn":[0.1286842631],"iteration":956,"passed_time":3.193775141,"remaining_time":0.1435029583},
{"learn":[0.1285996376],"iteration":957,"passed_time":3.197065843,"remaining_time":0.1401636382},
{"learn":[0.1285504605],"iteration":958,"passed_time":3.200225758,"remaining_time":0.136818828},
{"learn":[0.1284198536],"iteration":959,"passed_time":3.203754367,"remaining_time":0.1334897653},
{"learn":[0.128247105],"iteration":960,"passed_time":3.20694599,"remaining_time":0.1301466115},
{"learn":[0.1282093144],"iteration":961,"passed_time":3.21002845,"remaining_time":0.1267994606},
{"learn":[0.1281199377],"iteration":962,"passed_time":3.213228197,"remaining_time":0.1234573658},
{"learn":[0.1280506127],"iteration":963,"passed_time":3.216379655,"remaining_time":0.120113763},
{"learn":[0.1280484777],"iteration":964,"passed_time":3.218994217,"remaining_time":0.1167510856},
{"learn":[0.1280459746],"iteration":965,"passed_time":3.221904601,"remaining_time":0.113400369},
{"learn":[0.127901563],"iteration":966,"passed_time":3.225351421,"remaining_time":0.1100688696},
{"learn":[0.1278199801],"iteration":967,"passed_time":3.228242889,"remaining_time":0.1067187732},
{"learn":[0.1277451767],"iteration":968,"passed_time":3.231656836,"remaining_time":0.1033863384},
{"learn":[0.1276608537],"iteration":969,"passed_time":3.234732463,"remaining_time":0.1000432721},
{"learn":[0.1276585533],"iteration":970,"passed_time":3.237496561,"remaining_time":0.0966914524},
{"learn":[0.1276561639],"iteration":971,"passed_time":3.240382821,"remaining_time":0.0933443611},
{"learn":[0.1276447006],"iteration":972,"passed_time":3.24332187,"remaining_time":0.08999968191},
{"learn":[0.1275899205],"iteration":973,"passed_time":3.246229421,"remaining_time":0.08665499481},
{"learn":[0.1274783785],"iteration":974,"passed_time":3.25004881,"remaining_time":0.08333458487},
{"learn":[0.1274331058],"iteration":975,"passed_time":3.252924028,"remaining_time":0.07998993513},
{"learn":[0.1274308246],"iteration":976,"passed_time":3.255884327,"remaining_time":0.07664824925},
{"learn":[0.1273443036],"iteration":977,"passed_time":3.258893915,"remaining_time":0.07330845208},
{"learn":[0.1272853039],"iteration":978,"passed_time":3.261993,"remaining_time":0.06997124922},
{"learn":[0.1272577866],"iteration":979,"passed_time":3.264959423,"remaining_time":0.06663182495},
{"learn":[0.1272273103],"iteration":980,"passed_time":3.268058091,"remaining_time":0.06329572245},
{"learn":[0.127225076],"iteration":981,"passed_time":3.270803814,"remaining_time":0.05995363407},
{"learn":[0.1271060578],"iteration":982,"passed_time":3.274045393,"remaining_time":0.05662133437},
{"learn":[0.1270767184],"iteration":983,"passed_time":3.277059106,"remaining_time":0.05328551392},
{"learn":[0.1270738854],"iteration":984,"passed_time":3.27967971,"remaining_time":0.04994436106},
{"learn":[0.12705939],"iteration":985,"passed_time":3.282575052,"remaining_time":0.04660857072},
{"learn":[0.1269378135],"iteration":986,"passed_time":3.285652346,"remaining_time":0.0432760694},
{"learn":[0.1269356906],"iteration":987,"passed_time":3.288405153,"remaining_time":0.03994014356},
{"learn":[0.1268979122],"iteration":988,"passed_time":3.291945678,"remaining_time":0.0366141582},
{"learn":[0.12679352],"iteration":989,"passed_time":3.294841354,"remaining_time":0.0332812258},
{"learn":[0.1266906028],"iteration":990,"passed_time":3.29790994,"remaining_time":0.02995074618},
{"learn":[0.1265268979],"iteration":991,"passed_time":3.301404092,"remaining_time":0.02662422655},
{"learn":[0.1264316892],"iteration":992,"passed_time":3.304730251,"remaining_time":0.02329618505},
{"learn":[0.1263078496],"iteration":993,"passed_time":3.307765421,"remaining_time":0.01996639087},
{"learn":[0.126305873],"iteration":994,"passed_time":3.310583517,"remaining_time":0.01663609808},
{"learn":[0.1262934854],"iteration":995,"passed_time":3.313497984,"remaining_time":0.01330722082},
{"learn":[0.1262479322],"iteration":996,"passed_time":3.316293206,"remaining_time":0.009978816065},
{"learn":[0.1262258578],"iteration":997,"passed_time":3.319296794,"remaining_time":0.006651897383},
{"learn":[0.1262103438],"iteration":998,"passed_time":3.322001478,"remaining_time":0.003325326804},
{"learn":[0.1260710829],"iteration":999,"passed_time":3.325276055,"remaining_time":0}
]}